Workbook
Name Sale_Table: Table1[]
Name Slicer_Month: #N/A
Name Slicer_Payment_Method: #N/A
Name Slicer_States: #N/A

Sheet 01.Table
A1: Transaction ID | B1: Date | C1: Customer name | D1: Product | E1: Payment Method | F1: Unit Sold | G1: Buying Price | H1: Selling Price | I1: Total Buying | J1: Total Sales | K1: Profit | L1: States | M1: City | N1: Month
A2: T258 | B2: 45293 | C2: Rahul | D2: Headphones | E2: Cash | F2: 10 | G2: 6131.7 | H2: 7570 | I2: =F2*G2 -> 61317 | J2: 75700 | K2: =J2-I2 -> 14383 | L2: Uttar Pradesh | M2: Lucknow | N2: =TEXT(Table1[[#This Row],[Date]],"mmm") -> Jan
A3: T240 | B3: 45294 | C3: Rahul | D3: Headphones | E3: Cash | F3: 4 | G3: 42856.45 | H3: 47095 | I3: =F3*G3 -> 171425.8 | J3: 188380 | K3: =J3-I3 -> 16954.2 | L3: Uttar Pradesh | M3: Agra | N3: =TEXT(Table1[[#This Row],[Date]],"mmm") -> Jan
A4: T048 | B4: 45296 | C4: Karan | D4: Headphones | E4: Cash | F4: 2 | G4: 3289.29 | H4: 3963 | I4: ='01.Table'!$G4*'01.Table'!$F4 -> 6578.58 | J4: 7926 | K4: ='01.Table'!$J4-'01.Table'!$I4 -> 1347.42 | L4: Tamil Nadu | M4: Trichy | N4: =TEXT(Table1[[#This Row],[Date]],"mmm") -> Jan
A5: T202 | B5: 45296 | C5: Rahul | D5: Headphones | E5: Cash | F5: 6 | G5: 34115.31 | H5: 39213 | I5: =F5*G5 -> 204691.86 | J5: 235278 | K5: =J5-I5 -> 30586.14 | L5: Karnataka | M5: Davanagere | N5: =TEXT(Table1[[#This Row],[Date]],"mmm") -> Jan
A6: T228 | B6: 45298 | C6: Vikram | D6: Keyboard | E6: Cash | F6: 3 | G6: 12962.04 | H6: 15431 | I6: =F6*G6 -> 38886.12 | J6: 46293 | K6: =J6-I6 -> 7406.88 | L6: Karnataka | M6: Bengaluru | N6: =TEXT(Table1[[#This Row],[Date]],"mmm") -> Jan
A7: T016 | B7: 45301 | C7: Priya | D7: Tablet | E7: Online | F7: 2 | G7: 17407.26 | H7: 20241 | I7: ='01.Table'!$G36*'01.Table'!$F36 -> 20135.92 | J7: 40482 | K7: ='01.Table'!$J36-'01.Table'!$I36 -> 4420.08 | L7: Tamil Nadu | M7: Tirunelveli | N7: =TEXT(Table1[[#This Row],[Date]],"mmm") -> Jan
A8: T107 | B8: 45304 | C8: Rahul | D8: Monitor | E8: Cash | F8: 3 | G8: 26482.14 | H8: 32694 | I8: =F8*G8 -> 79446.42 | J8: 98082 | K8: =J8-I8 -> 18635.58 | L8: Gujarat | M8: Vadodara | N8: =TEXT(Table1[[#This Row],[Date]],"mmm") -> Jan
A9: T111 | B9: 45304 | C9: Shivam | D9: Monitor | E9: Cash | F9: 10 | G9: 19596.75 | H9: 22525 | I9: =F9*G9 -> 195967.5 | J9: 225250 | K9: =J9-I9 -> 29282.5 | L9: Karnataka | M9: Bengaluru | N9: =TEXT(Table1[[#This Row],[Date]],"mmm") -> Jan
A10: T134 | B10: 45304 | C10: Sneha | D10: Mouse | E10: Online | F10: 9 | G10: 19864.8 | H10: 24831 | I10: =F10*G10 -> 178783.2 | J10: 223479 | K10: =J10-I10 -> 44695.8 | L10: Tamil Nadu | M10: Tirunelveli | N10: =TEXT(Table1[[#This Row],[Date]],"mmm") -> Jan
A11: T136 | B11: 45304 | C11: Neha | D11: Keyboard | E11: Online | F11: 2 | G11: 36479.34 | H11: 44487 | I11: =F11*G11 -> 72958.68 | J11: 88974 | K11: =J11-I11 -> 16015.32 | L11: Karnataka | M11: Hubballi | N11: =TEXT(Table1[[#This Row],[Date]],"mmm") -> Jan
A12: T050 | B12: 45305 | C12: Neha | D12: Headphones | E12: Cash | F12: 10 | G12: 25648.8 | H12: 32061 | I12: ='01.Table'!$G6*'01.Table'!$F6 -> 38886.12 | J12: 320610 | K12: ='01.Table'!$J6-'01.Table'!$I6 -> 7406.88 | L12: Tamil Nadu | M12: Madurai | N12: =TEXT(Table1[[#This Row],[Date]],"mmm") -> Jan
A13: T026 | B13: 45306 | C13: Rahul | D13: Mouse | E13: Cash | F13: 5 | G13: 6872.42 | H13: 8381 | I13: ='01.Table'!$G23*'01.Table'!$F23 -> 216172 | J13: 41905 | K13: ='01.Table'!$J23-'01.Table'!$I23 -> 29478 | L13: Karnataka | M13: Mangaluru | N13: =TEXT(Table1[[#This Row],[Date]],"mmm") -> Jan
A14: T198 | B14: 45306 | C14: Sneha Gupta | D14: Monitor | E14: Cash | F14: 9 | G14: 7996 | H14: 9995 | I14: =F14*G14 -> 71964 | J14: 89955 | K14: =J14-I14 -> 17991 | L14: Gujarat | M14: Vadodara | N14: =TEXT(Table1[[#This Row],[Date]],"mmm") -> Jan
A15: T218 | B15: 45306 | C15: Karan | D15: Printer | E15: Cash | F15: 9 | G15: 25294.32 | H15: 29412 | I15: =F15*G15 -> 227648.88 | J15: 264708 | K15: =J15-I15 -> 37059.12 | L15: Maharashtra | M15: Nagpur | N15: =TEXT(Table1[[#This Row],[Date]],"mmm") -> Jan
A16: T269 | B16: 45307 | C16: Neha | D16: Mouse | E16: Online | F16: 5 | G16: 16778.96 | H16: 18238 | I16: =F16*G16 -> 83894.8 | J16: 91190 | K16: =J16-I16 -> 7295.2 | L16: Delhi | M16: Dwarka | N16: =TEXT(Table1[[#This Row],[Date]],"mmm") -> Jan
A17: T021 | B17: 45310 | C17: Shivam | D17: Printer | E17: Cash | F17: 5 | G17: 19801.36 | H17: 24148 | I17: ='01.Table'!$G28*'01.Table'!$F28 -> 38341.92 | J17: 120740 | K17: ='01.Table'!$J28-'01.Table'!$I28 -> 3334.08 | L17: Delhi | M17: New Delhi | N17: =TEXT(Table1[[#This Row],[Date]],"mmm") -> Jan
A18: T279 | B18: 45310 | C18: Anita | D18: Tablet | E18: Online | F18: 5 | G18: 32226.01 | H18: 36209 | I18: =F18*G18 -> 161130.05 | J18: 181045 | K18: =J18-I18 -> 19914.95 | L18: Delhi | M18: Karol Bagh | N18: =TEXT(Table1[[#This Row],[Date]],"mmm") -> Jan
A19: T252 | B19: 45313 | C19: Karan | D19: Monitor | E19: Cash | F19: 3 | G19: 22194.82 | H19: 24938 | I19: =F19*G19 -> 66584.46 | J19: 74814 | K19: =J19-I19 -> 8229.54 | L19: Uttar Pradesh | M19: Varanasi | N19: =TEXT(Table1[[#This Row],[Date]],"mmm") -> Jan
A20: T292 | B20: 45313 | C20: Shivam | D20: Headphones | E20: Online | F20: 5 | G20: 31449.6 | H20: 34560 | I20: =F20*G20 -> 157248 | J20: 172800 | K20: =J20-I20 -> 15552 | L20: Tamil Nadu | M20: Tirunelveli | N20: =TEXT(Table1[[#This Row],[Date]],"mmm") -> Jan
A21: T034 | B21: 45314 | C21: Sneha | D21: Monitor | E21: Cash | F21: 2 | G21: 15959.28 | H21: 18344 | I21: ='01.Table'!$G19*'01.Table'!$F19 -> 66584.46 | J21: 36688 | K21: ='01.Table'!$J19-'01.Table'!$I19 -> 8229.54 | L21: Karnataka | M21: Bengaluru | N21: =TEXT(Table1[[#This Row],[Date]],"mmm") -> Jan
A22: T226 | B22: 45318 | C22: Neha | D22: Headphones | E22: Online | F22: 6 | G22: 44541.9 | H22: 49491 | I22: =F22*G22 -> 267251.4 | J22: 296946 | K22: =J22-I22 -> 29694.6 | L22: Maharashtra | M22: Aurangabad | N22: =TEXT(Table1[[#This Row],[Date]],"mmm") -> Jan
A23: T290 | B23: 45319 | C23: Karan | D23: Printer | E23: Online | F23: 10 | G23: 21617.2 | H23: 24565 | I23: =F23*G23 -> 216172 | J23: 245650 | K23: =J23-I23 -> 29478 | L23: Tamil Nadu | M23: Madurai | N23: =TEXT(Table1[[#This Row],[Date]],"mmm") -> Jan
A24: T047 | B24: 45322 | C24: Sneha | D24: Headphones | E24: Cash | F24: 10 | G24: 7005.7 | H24: 8242 | I24: ='01.Table'!$G3*'01.Table'!$F3 -> 171425.8 | J24: 82420 | K24: ='01.Table'!$J3-'01.Table'!$I3 -> 16954.2 | L24: Tamil Nadu | M24: Chennai | N24: =TEXT(Table1[[#This Row],[Date]],"mmm") -> Jan
A25: T040 | B25: 45323 | C25: Shivam | D25: Laptop | E25: Online | F25: 4 | G25: 16722.26 | H25: 20393 | I25: ='01.Table'!$G15*'01.Table'!$F15 -> 227648.88 | J25: 81572 | K25: ='01.Table'!$J15-'01.Table'!$I15 -> 37059.12 | L25: Uttar Pradesh | M25: Noida | N25: =TEXT(Table1[[#This Row],[Date]],"mmm") -> Feb
A26: T073 | B26: 45325 | C26: Rahul | D26: Mouse | E26: Online | F26: 8 | G26: 24731.32 | H26: 27788 | I26: =F26*G26 -> 197850.56 | J26: 222304 | K26: =J26-I26 -> 24453.44 | L26: Tamil Nadu | M26: Coimbatore | N26: =TEXT(Table1[[#This Row],[Date]],"mmm") -> Feb
A27: T185 | B27: 45325 | C27: Neha | D27: Monitor | E27: Cash | F27: 10 | G27: 10941.6 | H27: 13677 | I27: =F27*G27 -> 109416 | J27: 136770 | K27: =J27-I27 -> 27354 | L27: Tamil Nadu | M27: Salem | N27: =TEXT(Table1[[#This Row],[Date]],"mmm") -> Feb
A28: T179 | B28: 45326 | C28: Rahul | D28: Tablet | E28: Online | F28: 2 | G28: 19170.96 | H28: 20838 | I28: =F28*G28 -> 38341.92 | J28: 41676 | K28: =J28-I28 -> 3334.08 | L28: Maharashtra | M28: Aurangabad | N28: =TEXT(Table1[[#This Row],[Date]],"mmm") -> Feb
A29: T186 | B29: 45330 | C29: Vikram | D29: Mouse | E29: Cash | F29: 6 | G29: 3752.73 | H29: 4633 | I29: =F29*G29 -> 22516.38 | J29: 27798 | K29: =J29-I29 -> 5281.62 | L29: Delhi | M29: Karol Bagh | N29: =TEXT(Table1[[#This Row],[Date]],"mmm") -> Feb
A30: T004 | B30: 45331 | C30: Rahul | D30: Webcam | E30: Cash | F30: 5 | G30: 8220.04 | H30: 9236 | I30: ='01.Table'!$G44*'01.Table'!$F44 -> 51111 | J30: 46180 | K30: ='01.Table'!$J44-'01.Table'!$I44 -> 5679 | L30: Uttar Pradesh | M30: Lucknow | N30: =TEXT(Table1[[#This Row],[Date]],"mmm") -> Feb
A31: T151 | B31: 45332 | C31: Priya Gupta | D31: Laptop | E31: Online | F31: 2 | G31: 22920.48 | H31: 26046 | I31: =F31*G31 -> 45840.96 | J31: 52092 | K31: =J31-I31 -> 6251.04 | L31: Karnataka | M31: Davanagere | N31: =TEXT(Table1[[#This Row],[Date]],"mmm") -> Feb
A32: T099 | B32: 45333 | C32: Priya | D32: Mouse | E32: Online | F32: 7 | G32: 44021.7 | H32: 48913 | I32: =F32*G32 -> 308151.9 | J32: 342391 | K32: =J32-I32 -> 34239.1 | L32: Uttar Pradesh | M32: Ghaziabad | N32: =TEXT(Table1[[#This Row],[Date]],"mmm") -> Feb
A33: T270 | B33: 45333 | C33: Rahul | D33: Printer | E33: Cash | F33: 4 | G33: 36675 | H33: 40750 | I33: =F33*G33 -> 146700 | J33: 163000 | K33: =J33-I33 -> 16300 | L33: Uttar Pradesh | M33: Kanpur | N33: =TEXT(Table1[[#This Row],[Date]],"mmm") -> Feb
A34: T075 | B34: 45334 | C34: Sneha Gupta | D34: Mouse | E34: Online | F34: 8 | G34: 23217.12 | H34: 25236 | I34: =F34*G34 -> 185736.96 | J34: 201888 | K34: =J34-I34 -> 16151.04 | L34: Uttar Pradesh | M34: Ghaziabad | N34: =TEXT(Table1[[#This Row],[Date]],"mmm") -> Feb
A35: T217 | B35: 45337 | C35: Neha | D35: Monitor | E35: Online | F35: 4 | G35: 5816.7 | H35: 6463 | I35: =F35*G35 -> 23266.8 | J35: 25852 | K35: =J35-I35 -> 2585.2 | L35: Tamil Nadu | M35: Coimbatore | N35: =TEXT(Table1[[#This Row],[Date]],"mmm") -> Feb
A36: T203 | B36: 45338 | C36: Sneha Gupta | D36: Mouse | E36: Cash | F36: 7 | G36: 2876.56 | H36: 3508 | I36: =F36*G36 -> 20135.92 | J36: 24556 | K36: =J36-I36 -> 4420.08 | L36: Uttar Pradesh | M36: Kanpur | N36: =TEXT(Table1[[#This Row],[Date]],"mmm") -> Feb
A37: T093 | B37: 45342 | C37: Pooja | D37: Monitor | E37: Cash | F37: 5 | G37: 32358.65 | H37: 38069 | I37: =F37*G37 -> 161793.25 | J37: 190345 | K37: =J37-I37 -> 28551.75 | L37: Delhi | M37: New Delhi | N37: =TEXT(Table1[[#This Row],[Date]],"mmm") -> Feb
A38: T140 | B38: 45342 | C38: Shivam | D38: Laptop | E38: Cash | F38: 2 | G38: 32589 | H38: 36210 | I38: =F38*G38 -> 65178 | J38: 72420 | K38: =J38-I38 -> 7242 | L38: Tamil Nadu | M38: Trichy | N38: =TEXT(Table1[[#This Row],[Date]],"mmm") -> Feb
A39: T020 | B39: 45343 | C39: Rahul | D39: Tablet | E39: Online | F39: 3 | G39: 23503.5 | H39: 26115 | I39: ='01.Table'!$G40*'01.Table'!$F40 -> 53041.98 | J39: 78345 | K39: ='01.Table'!$J40-'01.Table'!$I40 -> 10864.02 | L39: Uttar Pradesh | M39: Varanasi | N39: =TEXT(Table1[[#This Row],[Date]],"mmm") -> Feb
A40: T077 | B40: 45344 | C40: Anita | D40: Laptop | E40: Cash | F40: 2 | G40: 26520.99 | H40: 31953 | I40: =F40*G40 -> 53041.98 | J40: 63906 | K40: =J40-I40 -> 10864.02 | L40: Uttar Pradesh | M40: Noida | N40: =TEXT(Table1[[#This Row],[Date]],"mmm") -> Feb
A41: T150 | B41: 45344 | C41: Priya Gupta | D41: Webcam | E41: Online | F41: 3 | G41: 38984.27 | H41: 46969 | I41: =F41*G41 -> 116952.81 | J41: 140907 | K41: =J41-I41 -> 23954.19 | L41: Maharashtra | M41: Thane | N41: =TEXT(Table1[[#This Row],[Date]],"mmm") -> Feb
A42: T135 | B42: 45346 | C42: Priya | D42: Headphones | E42: Online | F42: 7 | G42: 28274.61 | H42: 31071 | I42: =F42*G42 -> 197922.27 | J42: 217497 | K42: =J42-I42 -> 19574.73 | L42: Maharashtra | M42: Pune | N42: =TEXT(Table1[[#This Row],[Date]],"mmm") -> Feb
A43: T071 | B43: 45348 | C43: Pooja | D43: Printer | E43: Online | F43: 2 | G43: 43699.08 | H43: 47499 | I43: =F43*G43 -> 87398.16 | J43: 94998 | K43: =J43-I43 -> 7599.84 | L43: Karnataka | M43: Mysuru | N43: =TEXT(Table1[[#This Row],[Date]],"mmm") -> Feb
A44: T149 | B44: 45348 | C44: Shivam | D44: Keyboard | E44: Cash | F44: 3 | G44: 17037 | H44: 18930 | I44: =F44*G44 -> 51111 | J44: 56790 | K44: =J44-I44 -> 5679 | L44: Uttar Pradesh | M44: Lucknow | N44: =TEXT(Table1[[#This Row],[Date]],"mmm") -> Feb
A45: T175 | B45: 45348 | C45: Priya Gupta | D45: Webcam | E45: Online | F45: 3 | G45: 31798.5 | H45: 36975 | I45: =F45*G45 -> 95395.5 | J45: 110925 | K45: =J45-I45 -> 15529.5 | L45: Delhi | M45: Karol Bagh | N45: =TEXT(Table1[[#This Row],[Date]],"mmm") -> Feb
A46: T277 | B46: 45349 | C46: Priya Gupta | D46: Printer | E46: Online | F46: 10 | G46: 8394.6 | H46: 9876 | I46: =F46*G46 -> 83946 | J46: 98760 | K46: =J46-I46 -> 14814 | L46: Gujarat | M46: Rajkot | N46: =TEXT(Table1[[#This Row],[Date]],"mmm") -> Feb
A47: T074 | B47: 45350 | C47: Rahul | D47: Keyboard | E47: Cash | F47: 2 | G47: 10383.2 | H47: 12979 | I47: =F47*G47 -> 20766.4 | J47: 25958 | K47: =J47-I47 -> 5191.6 | L47: Uttar Pradesh | M47: Kanpur | N47: =TEXT(Table1[[#This Row],[Date]],"mmm") -> Feb
A48: T079 | B48: 45350 | C48: Rahul | D48: Webcam | E48: Online | F48: 4 | G48: 34990.35 | H48: 39315 | I48: =F48*G48 -> 139961.4 | J48: 157260 | K48: =J48-I48 -> 17298.6 | L48: Maharashtra | M48: Aurangabad | N48: =TEXT(Table1[[#This Row],[Date]],"mmm") -> Feb
A49: T257 | B49: 45350 | C49: Priya | D49: Headphones | E49: Online | F49: 8 | G49: 40431.96 | H49: 49916 | I49: =F49*G49 -> 323455.68 | J49: 399328 | K49: =J49-I49 -> 75872.32 | L49: Gujarat | M49: Rajkot | N49: =TEXT(Table1[[#This Row],[Date]],"mmm") -> Feb
A50: T058 | B50: 45351 | C50: Sneha Gupta | D50: Webcam | E50: Cash | F50: 5 | G50: 28927.36 | H50: 32872 | I50: =F50*G50 -> 144636.8 | J50: 164360 | K50: =J50-I50 -> 19723.2 | L50: Maharashtra | M50: Nashik | N50: =TEXT(Table1[[#This Row],[Date]],"mmm") -> Feb
A51: T120 | B51: 45351 | C51: Priya Gupta | D51: Monitor | E51: Online | F51: 3 | G51: 20670.39 | H51: 25519 | I51: =F51*G51 -> 62011.17 | J51: 76557 | K51: =J51-I51 -> 14545.83 | L51: Gujarat | M51: Rajkot | N51: =TEXT(Table1[[#This Row],[Date]],"mmm") -> Feb
... A54: T156 | B54: 45355 | C54: Vikram | D54: Headphones | E54: Cash | F54: 3 | G54: 7528.93 | H54: 9071 | I54: =F54*G54 -> 22586.79 | J54: 27213 | K54: =J54-I54 -> 4626.21 | L54: Tamil Nadu | M54: Madurai | N54: =TEXT(Table1[[#This Row],[Date]],"mmm") -> Mar
A55: T008 | B55: 45357 | C55: Shivam | D55: Webcam | E55: Online | F55: 5 | G55: 36531 | H55: 40590 | I55: ='01.Table'!$G48*'01.Table'!$F48 -> 139961.4 | J55: 202950 | K55: ='01.Table'!$J48-'01.Table'!$I48 -> 17298.6 | L55: Delhi | M55: Saket | N55: =TEXT(Table1[[#This Row],[Date]],"mmm") -> Mar
A56: T238 | B56: 45357 | C56: Shivam | D56: Headphones | E56: Online | F56: 8 | G56: 18575.05 | H56: 21853 | I56: =F56*G56 -> 148600.4 | J56: 174824 | K56: =J56-I56 -> 26223.6 | L56: Delhi | M56: New Delhi | N56: =TEXT(Table1[[#This Row],[Date]],"mmm") -> Mar
A57: T117 | B57: 45358 | C57: Priya | D57: Laptop | E57: Cash | F57: 3 | G57: 4250.12 | H57: 4942 | I57: =F57*G57 -> 12750.36 | J57: 14826 | K57: =J57-I57 -> 2075.64 | L57: Karnataka | M57: Hubballi | N57: =TEXT(Table1[[#This Row],[Date]],"mmm") -> Mar
A58: T194 | B58: 45360 | C58: Shivam | D58: Mouse | E58: Online | F58: 6 | G58: 1926.47 | H58: 2117 | I58: =F58*G58 -> 11558.82 | J58: 12702 | K58: =J58-I58 -> 1143.18 | L58: Uttar Pradesh | M58: Ghaziabad | N58: =TEXT(Table1[[#This Row],[Date]],"mmm") -> Mar
A59: T280 | B59: 45361 | C59: Rahul | D59: Printer | E59: Cash | F59: 4 | G59: 22545.6 | H59: 25620 | I59: =F59*G59 -> 90182.4 | J59: 102480 | K59: =J59-I59 -> 12297.6 | L59: Karnataka | M59: Hubballi | N59: =TEXT(Table1[[#This Row],[Date]],"mmm") -> Mar
A60: T022 | B60: 45362 | C60: Vikram | D60: Printer | E60: Online | F60: 1 | G60: 43800.24 | H60: 49773 | I60: ='01.Table'!$G29*'01.Table'!$F29 -> 22516.38 | J60: 49773 | K60: ='01.Table'!$J29-'01.Table'!$I29 -> 5281.62 | L60: Maharashtra | M60: Thane | N60: =TEXT(Table1[[#This Row],[Date]],"mmm") -> Mar
A61: T007 | B61: 45362 | C61: Sneha | D61: Webcam | E61: Cash | F61: 7 | G61: 29657.12 | H61: 32236 | I61: ='01.Table'!$G47*'01.Table'!$F47 -> 20766.4 | J61: 225652 | K61: ='01.Table'!$J47-'01.Table'!$I47 -> 5191.6 | L61: Tamil Nadu | M61: Madurai | N61: =TEXT(Table1[[#This Row],[Date]],"mmm") -> Mar
A62: T188 | B62: 45362 | C62: Vikram | D62: Tablet | E62: Cash | F62: 7 | G62: 33002.97 | H62: 36267 | I62: =F62*G62 -> 231020.79 | J62: 253869 | K62: =J62-I62 -> 22848.21 | L62: Delhi | M62: Karol Bagh | N62: =TEXT(Table1[[#This Row],[Date]],"mmm") -> Mar
A63: T169 | B63: 45363 | C63: Sneha | D63: Mouse | E63: Online | F63: 4 | G63: 22304.19 | H63: 25637 | I63: =F63*G63 -> 89216.76 | J63: 102548 | K63: =J63-I63 -> 13331.24 | L63: Maharashtra | M63: Mumbai | N63: =TEXT(Table1[[#This Row],[Date]],"mmm") -> Mar
A64: T300 | B64: 45364 | C64: Priya Gupta | D64: Mouse | E64: Cash | F64: 10 | G64: 12957.62 | H64: 15067 | I64: =F64*G64 -> 129576.2 | J64: 150670 | K64: =J64-I64 -> 21093.8 | L64: Maharashtra | M64: Mumbai | N64: =TEXT(Table1[[#This Row],[Date]],"mmm") -> Mar
A65: T076 | B65: 45365 | C65: Priya | D65: Laptop | E65: Online | F65: 3 | G65: 8328.32 | H65: 9152 | I65: =F65*G65 -> 24984.96 | J65: 27456 | K65: =J65-I65 -> 2471.04 | L65: Karnataka | M65: Belagavi | N65: =TEXT(Table1[[#This Row],[Date]],"mmm") -> Mar
A66: T230 | B66: 45366 | C66: Neha | D66: Webcam | E66: Cash | F66: 3 | G66: 31181.88 | H66: 36258 | I66: =F66*G66 -> 93545.64 | J66: 108774 | K66: =J66-I66 -> 15228.36 | L66: Delhi | M66: Karol Bagh | N66: =TEXT(Table1[[#This Row],[Date]],"mmm") -> Mar
A67: T249 | B67: 45366 | C67: Priya Gupta | D67: Mouse | E67: Online | F67: 7 | G67: 2070.4 | H67: 2588 | I67: =F67*G67 -> 14492.8 | J67: 18116 | K67: =J67-I67 -> 3623.2 | L67: Karnataka | M67: Belagavi | N67: =TEXT(Table1[[#This Row],[Date]],"mmm") -> Mar
A68: T094 | B68: 45367 | C68: Sneha | D68: Keyboard | E68: Online | F68: 7 | G68: 13947.2 | H68: 15160 | I68: =F68*G68 -> 97630.4 | J68: 106120 | K68: =J68-I68 -> 8489.6 | L68: Karnataka | M68: Mysuru | N68: =TEXT(Table1[[#This Row],[Date]],"mmm") -> Mar
A69: T229 | B69: 45368 | C69: Vikram | D69: Monitor | E69: Cash | F69: 9 | G69: 24146.54 | H69: 29447 | I69: =F69*G69 -> 217318.86 | J69: 265023 | K69: =J69-I69 -> 47704.14 | L69: Karnataka | M69: Hubballi | N69: =TEXT(Table1[[#This Row],[Date]],"mmm") -> Mar
A70: T028 | B70: 45370 | C70: Anita | D70: Mouse | E70: Online | F70: 7 | G70: 22979.04 | H70: 27356 | I70: ='01.Table'!$G25*'01.Table'!$F25 -> 66889.04 | J70: 191492 | K70: ='01.Table'!$J25-'01.Table'!$I25 -> -146076.88 | L70: Uttar Pradesh | M70: Varanasi | N70: =TEXT(Table1[[#This Row],[Date]],"mmm") -> Mar
A71: T126 | B71: 45372 | C71: Anita | D71: Printer | E71: Online | F71: 1 | G71: 18895.2 | H71: 23619 | I71: =F71*G71 -> 18895.2 | J71: 23619 | K71: =J71-I71 -> 4723.8 | L71: Delhi | M71: Karol Bagh | N71: =TEXT(Table1[[#This Row],[Date]],"mmm") -> Mar
A72: T059 | B72: 45373 | C72: Pooja | D72: Tablet | E72: Online | F72: 9 | G72: 4181.6 | H72: 5227 | I72: =F72*G72 -> 37634.4 | J72: 47043 | K72: =J72-I72 -> 9408.6 | L72: Uttar Pradesh | M72: Varanasi | N72: =TEXT(Table1[[#This Row],[Date]],"mmm") -> Mar
A73: T297 | B73: 45374 | C73: Pooja | D73: Tablet | E73: Cash | F73: 3 | G73: 41386.2 | H73: 44985 | I73: =F73*G73 -> 124158.6 | J73: 134955 | K73: =J73-I73 -> 10796.4 | L73: Tamil Nadu | M73: Salem | N73: =TEXT(Table1[[#This Row],[Date]],"mmm") -> Mar
A74: T271 | B74: 45376 | C74: Sneha | D74: Laptop | E74: Cash | F74: 2 | G74: 45203.28 | H74: 49134 | I74: =F74*G74 -> 90406.56 | J74: 98268 | K74: =J74-I74 -> 7861.44 | L74: Karnataka | M74: Hubballi | N74: =TEXT(Table1[[#This Row],[Date]],"mmm") -> Mar
A75: T162 | B75: 45378 | C75: Rahul | D75: Laptop | E75: Cash | F75: 6 | G75: 35053.84 | H75: 38102 | I75: =F75*G75 -> 210323.04 | J75: 228612 | K75: =J75-I75 -> 18288.96 | L75: Tamil Nadu | M75: Trichy | N75: =TEXT(Table1[[#This Row],[Date]],"mmm") -> Mar
A76: T083 | B76: 45379 | C76: Karan | D76: Tablet | E76: Online | F76: 8 | G76: 35734.72 | H76: 41552 | I76: =F76*G76 -> 285877.76 | J76: 332416 | K76: =J76-I76 -> 46538.24 | L76: Gujarat | M76: Vadodara | N76: =TEXT(Table1[[#This Row],[Date]],"mmm") -> Mar
A77: T122 | B77: 45379 | C77: Karan | D77: Tablet | E77: Cash | F77: 6 | G77: 11215.72 | H77: 12191 | I77: =F77*G77 -> 67294.32 | J77: 73146 | K77: =J77-I77 -> 5851.68 | L77: Uttar Pradesh | M77: Varanasi | N77: =TEXT(Table1[[#This Row],[Date]],"mmm") -> Mar
A78: T224 | B78: 45380 | C78: Rahul | D78: Monitor | E78: Online | F78: 5 | G78: 6798.6 | H78: 7554 | I78: =F78*G78 -> 33993 | J78: 37770 | K78: =J78-I78 -> 3777 | L78: Tamil Nadu | M78: Chennai | N78: =TEXT(Table1[[#This Row],[Date]],"mmm") -> Mar
A79: T161 | B79: 45381 | C79: Sneha | D79: Webcam | E79: Cash | F79: 7 | G79: 11124.96 | H79: 12936 | I79: =F79*G79 -> 77874.72 | J79: 90552 | K79: =J79-I79 -> 12677.28 | L79: Gujarat | M79: Vadodara | N79: =TEXT(Table1[[#This Row],[Date]],"mmm") -> Mar
A80: T029 | B80: 45382 | C80: Pooja | D80: Mouse | E80: Cash | F80: 4 | G80: 26208 | H80: 29120 | I80: ='01.Table'!$G26*'01.Table'!$F26 -> 197850.56 | J80: 116480 | K80: ='01.Table'!$J26-'01.Table'!$I26 -> 24453.44 | L80: Tamil Nadu | M80: Salem | N80: =TEXT(Table1[[#This Row],[Date]],"mmm") -> Mar
A81: T242 | B81: 45382 | C81: Sneha Gupta | D81: Laptop | E81: Online | F81: 4 | G81: 7439.4 | H81: 8266 | I81: =F81*G81 -> 29757.6 | J81: 33064 | K81: =J81-I81 -> 3306.4 | L81: Maharashtra | M81: Thane | N81: =TEXT(Table1[[#This Row],[Date]],"mmm") -> Mar
A82: T116 | B82: 45384 | C82: Sneha | D82: Mouse | E82: Cash | F82: 4 | G82: 6825.91 | H82: 7501 | I82: =F82*G82 -> 27303.64 | J82: 30004 | K82: =J82-I82 -> 2700.36 | L82: Karnataka | M82: Belagavi | N82: =TEXT(Table1[[#This Row],[Date]],"mmm") -> Apr
A83: T195 | B83: 45385 | C83: Neha | D83: Tablet | E83: Online | F83: 2 | G83: 21974.36 | H83: 26798 | I83: =F83*G83 -> 43948.72 | J83: 53596 | K83: =J83-I83 -> 9647.28 | L83: Gujarat | M83: Jamnagar | N83: =TEXT(Table1[[#This Row],[Date]],"mmm") -> Apr
A84: T060 | B84: 45386 | C84: Sneha Gupta | D84: Printer | E84: Online | F84: 5 | G84: 18589.6 | H84: 23237 | I84: =F84*G84 -> 92948 | J84: 116185 | K84: =J84-I84 -> 23237 | L84: Maharashtra | M84: Pune | N84: =TEXT(Table1[[#This Row],[Date]],"mmm") -> Apr
A85: T011 | B85: 45389 | C85: Anita | D85: Webcam | E85: Cash | F85: 9 | G85: 35264 | H85: 44080 | I85: ='01.Table'!$G51*'01.Table'!$F51 -> 62011.17 | J85: 396720 | K85: ='01.Table'!$J51-'01.Table'!$I51 -> 14545.83 | L85: Karnataka | M85: Bengaluru | N85: =TEXT(Table1[[#This Row],[Date]],"mmm") -> Apr
A86: T090 | B86: 45389 | C86: Rahul | D86: Keyboard | E86: Online | F86: 3 | G86: 40086.48 | H86: 47722 | I86: =F86*G86 -> 120259.44 | J86: 143166 | K86: =J86-I86 -> 22906.56 | L86: Uttar Pradesh | M86: Noida | N86: =TEXT(Table1[[#This Row],[Date]],"mmm") -> Apr
A87: T259 | B87: 45390 | C87: Neha | D87: Mouse | E87: Online | F87: 8 | G87: 12060.9 | H87: 14890 | I87: =F87*G87 -> 96487.2 | J87: 119120 | K87: =J87-I87 -> 22632.8 | L87: Delhi | M87: New Delhi | N87: =TEXT(Table1[[#This Row],[Date]],"mmm") -> Apr
A88: T193 | B88: 45391 | C88: Neha | D88: Headphones | E88: Cash | F88: 7 | G88: 11119.68 | H88: 12636 | I88: =F88*G88 -> 77837.76 | J88: 88452 | K88: =J88-I88 -> 10614.24 | L88: Gujarat | M88: Jamnagar | N88: =TEXT(Table1[[#This Row],[Date]],"mmm") -> Apr
A89: T046 | B89: 45392 | C89: Neha | D89: Headphones | E89: Online | F89: 1 | G89: 32454.7 | H89: 38182 | I89: ='01.Table'!$G2*'01.Table'!$F2 -> 61317 | J89: 38182 | K89: ='01.Table'!$J2-'01.Table'!$I2 -> 14383 | L89: Uttar Pradesh | M89: Kanpur | N89: =TEXT(Table1[[#This Row],[Date]],"mmm") -> Apr
A90: T130 | B90: 45393 | C90: Sneha | D90: Laptop | E90: Cash | F90: 4 | G90: 13546.72 | H90: 15394 | I90: =F90*G90 -> 54186.88 | J90: 61576 | K90: =J90-I90 -> 7389.12 | L90: Delhi | M90: Connaught Place | N90: =TEXT(Table1[[#This Row],[Date]],"mmm") -> Apr
A91: T181 | B91: 45394 | C91: Anita | D91: Headphones | E91: Cash | F91: 5 | G91: 38295.84 | H91: 43518 | I91: =F91*G91 -> 191479.2 | J91: 217590 | K91: =J91-I91 -> 26110.8 | L91: Karnataka | M91: Hubballi | N91: =TEXT(Table1[[#This Row],[Date]],"mmm") -> Apr
A92: T184 | B92: 45398 | C92: Anita | D92: Webcam | E92: Online | F92: 8 | G92: 12413.7 | H92: 13793 | I92: =F92*G92 -> 99309.6 | J92: 110344 | K92: =J92-I92 -> 11034.4 | L92: Uttar Pradesh | M92: Agra | N92: =TEXT(Table1[[#This Row],[Date]],"mmm") -> Apr
A93: T141 | B93: 45400 | C93: Priya | D93: Mouse | E93: Online | F93: 10 | G93: 4662.4 | H93: 5828 | I93: =F93*G93 -> 46624 | J93: 58280 | K93: =J93-I93 -> 11656 | L93: Delhi | M93: Rohini | N93: =TEXT(Table1[[#This Row],[Date]],"mmm") -> Apr
A94: T119 | B94: 45401 | C94: Vikram | D94: Laptop | E94: Cash | F94: 10 | G94: 20709.9 | H94: 23011 | I94: =F94*G94 -> 207099 | J94: 230110 | K94: =J94-I94 -> 23011 | L94: Karnataka | M94: Mysuru | N94: =TEXT(Table1[[#This Row],[Date]],"mmm") -> Apr
A95: T248 | B95: 45401 | C95: Sneha | D95: Keyboard | E95: Online | F95: 6 | G95: 37120.09 | H95: 44723 | I95: =F95*G95 -> 222720.54 | J95: 268338 | K95: =J95-I95 -> 45617.46 | L95: Delhi | M95: Rohini | N95: =TEXT(Table1[[#This Row],[Date]],"mmm") -> Apr
A96: T096 | B96: 45402 | C96: Pooja | D96: Mouse | E96: Online | F96: 1 | G96: 10689.57 | H96: 12879 | I96: =F96*G96 -> 10689.57 | J96: 12879 | K96: =J96-I96 -> 2189.43 | L96: Delhi | M96: Saket | N96: =TEXT(Table1[[#This Row],[Date]],"mmm") -> Apr
A97: T024 | B97: 45403 | C97: Anita | D97: Printer | E97: Cash | F97: 5 | G97: 17990.73 | H97: 20679 | I97: ='01.Table'!$G31*'01.Table'!$F31 -> 45840.96 | J97: 103395 | K97: ='01.Table'!$J31-'01.Table'!$I31 -> 6251.04 | L97: Karnataka | M97: Hubballi | N97: =TEXT(Table1[[#This Row],[Date]],"mmm") -> Apr
A98: T171 | B98: 45403 | C98: Sneha | D98: Headphones | E98: Online | F98: 4 | G98: 9478.92 | H98: 11022 | I98: =F98*G98 -> 37915.68 | J98: 44088 | K98: =J98-I98 -> 6172.32 | L98: Gujarat | M98: Surat | N98: =TEXT(Table1[[#This Row],[Date]],"mmm") -> Apr
A99: T210 | B99: 45405 | C99: Sneha | D99: Mouse | E99: Online | F99: 6 | G99: 17031.6 | H99: 20520 | I99: =F99*G99 -> 102189.6 | J99: 123120 | K99: =J99-I99 -> 20930.4 | L99: Karnataka | M99: Hubballi | N99: =TEXT(Table1[[#This Row],[Date]],"mmm") -> Apr
A100: T165 | B100: 45406 | C100: Vikram | D100: Mouse | E100: Cash | F100: 5 | G100: 8568.09 | H100: 10323 | I100: =F100*G100 -> 42840.45 | J100: 51615 | K100: =J100-I100 -> 8774.55 | L100: Karnataka | M100: Mysuru | N100: =TEXT(Table1[[#This Row],[Date]],"mmm") -> Apr
A101: T035 | B101: 45407 | C101: Sneha | D101: Monitor | E101: Online | F101: 6 | G101: 27739.36 | H101: 31522 | I101: ='01.Table'!$G20*'01.Table'!$F20 -> 157248 | J101: 189132 | K101: ='01.Table'!$J20-'01.Table'!$I20 -> 15552 | L101: Maharashtra | M101: Nashik | N101: =TEXT(Table1[[#This Row],[Date]],"mmm") -> Apr
A102: T286 | B102: 45407 | C102: Sneha | D102: Headphones | E102: Cash | F102: 6 | G102: 40296.5 | H102: 48550 | I102: =F102*G102 -> 241779 | J102: 291300 | K102: =J102-I102 -> 49521 | L102: Maharashtra | M102: Mumbai | N102: =TEXT(Table1[[#This Row],[Date]],"mmm") -> Apr
...

Sheet 02.MIS Report Table
A1: =IF(ISEVEN('07.DRW'!K4),"Total Sales","Total Profit") -> Total Profit
A5: Customer name/Product | B5: Online | J5: Cash | R5: Total
B6: Headphones | C6: Keyboard | D6: Laptop | E6: Monitor | F6: Mouse | G6: Printer | H6: Tablet | I6: Webcam | J6: Headphones | K6: Keyboard | L6: Laptop | M6: Monitor | N6: Mouse | O6: Printer | P6: Tablet | Q6: Webcam
A7: Neha | B7: =SUMIFS(IF(ISEVEN('07.DRW'!$K$4),INDEX(Table1[],,10),INDEX(Table1[],,11)), Table1[[Customer name]:[Customer name]], '02.MIS Report Table'!$A7, Table1[[Payment Method]:[Payment Method]], "Online", Table1[[Product]:[Product]], '02.MIS Report Table'!B$6) -> 60772.6 | C7: =SUMIFS(IF(ISEVEN('07.DRW'!$K$4),INDEX(Table1[],,10),INDEX(Table1[],,11)), Table1[[Customer name]:[Customer name]], '02.MIS Report Table'!$A7, Table1[[Payment Method]:[Payment Method]], "Online", Table1[[Product]:[Product]], '02.MIS Report Table'!C$6) -> 16015.32 | D7: =SUMIFS(IF(ISEVEN('07.DRW'!$K$4),INDEX(Table1[],,10),INDEX(Table1[],,11)), Table1[[Customer name]:[Customer name]], '02.MIS Report Table'!$A7, Table1[[Payment Method]:[Payment Method]], "Online", Table1[[Product]:[Product]], '02.MIS Report Table'!D$6) -> 0 | E7: =SUMIFS(IF(ISEVEN('07.DRW'!$K$4),INDEX(Table1[],,10),INDEX(Table1[],,11)), Table1[[Customer name]:[Customer name]], '02.MIS Report Table'!$A7, Table1[[Payment Method]:[Payment Method]], "Online", Table1[[Product]:[Product]], '02.MIS Report Table'!E$6) -> 11079.4 | F7: =SUMIFS(IF(ISEVEN('07.DRW'!$K$4),INDEX(Table1[],,10),INDEX(Table1[],,11)), Table1[[Customer name]:[Customer name]], '02.MIS Report Table'!$A7, Table1[[Payment Method]:[Payment Method]], "Online", Table1[[Product]:[Product]], '02.MIS Report Table'!F$6) -> 48256.97 | G7: =SUMIFS(IF(ISEVEN('07.DRW'!$K$4),INDEX(Table1[],,10),INDEX(Table1[],,11)), Table1[[Customer name]:[Customer name]], '02.MIS Report Table'!$A7, Table1[[Payment Method]:[Payment Method]], "Online", Table1[[Product]:[Product]], '02.MIS Report Table'!G$6) -> 13164.48 | H7: =SUMIFS(IF(ISEVEN('07.DRW'!$K$4),INDEX(Table1[],,10),INDEX(Table1[],,11)), Table1[[Customer name]:[Customer name]], '02.MIS Report Table'!$A7, Table1[[Payment Method]:[Payment Method]], "Online", Table1[[Product]:[Product]], '02.MIS Report Table'!H$6) -> 9647.28 | I7: =SUMIFS(IF(ISEVEN('07.DRW'!$K$4),INDEX(Table1[],,10),INDEX(Table1[],,11)), Table1[[Customer name]:[Customer name]], '02.MIS Report Table'!$A7, Table1[[Payment Method]:[Payment Method]], "Online", Table1[[Product]:[Product]], '02.MIS Report Table'!I$6) -> 9212 | J7: =SUMIFS(IF(ISEVEN('07.DRW'!$K$4),INDEX(Table1[],,10),INDEX(Table1[],,11)), Table1[[Customer name]:[Customer name]], '02.MIS Report Table'!$A7, Table1[[Payment Method]:[Payment Method]], "Cash", Table1[[Product]:[Product]], '02.MIS Report Table'!B$6) -> 18021.12 | K7: =SUMIFS(IF(ISEVEN('07.DRW'!$K$4),INDEX(Table1[],,10),INDEX(Table1[],,11)), Table1[[Customer name]:[Customer name]], '02.MIS Report Table'!$A7, Table1[[Payment Method]:[Payment Method]], "Cash", Table1[[Product]:[Product]], '02.MIS Report Table'!C$6) -> 0 | L7: =SUMIFS(IF(ISEVEN('07.DRW'!$K$4),INDEX(Table1[],,10),INDEX(Table1[],,11)), Table1[[Customer name]:[Customer name]], '02.MIS Report Table'!$A7, Table1[[Payment Method]:[Payment Method]], "Cash", Table1[[Product]:[Product]], '02.MIS Report Table'!D$6) -> 0 | M7: =SUMIFS(IF(ISEVEN('07.DRW'!$K$4),INDEX(Table1[],,10),INDEX(Table1[],,11)), Table1[[Customer name]:[Customer name]], '02.MIS Report Table'!$A7, Table1[[Payment Method]:[Payment Method]], "Cash", Table1[[Product]:[Product]], '02.MIS Report Table'!E$6) -> 35759.6 | N7: =SUMIFS(IF(ISEVEN('07.DRW'!$K$4),INDEX(Table1[],,10),INDEX(Table1[],,11)), Table1[[Customer name]:[Customer name]], '02.MIS Report Table'!$A7, Table1[[Payment Method]:[Payment Method]], "Cash", Table1[[Product]:[Product]], '02.MIS Report Table'!F$6) -> 39405.6 | O7: =SUMIFS(IF(ISEVEN('07.DRW'!$K$4),INDEX(Table1[],,10),INDEX(Table1[],,11)), Table1[[Customer name]:[Customer name]], '02.MIS Report Table'!$A7, Table1[[Payment Method]:[Payment Method]], "Cash", Table1[[Product]:[Product]], '02.MIS Report Table'!G$6) -> 108580 | P7: =SUMIFS(IF(ISEVEN('07.DRW'!$K$4),INDEX(Table1[],,10),INDEX(Table1[],,11)), Table1[[Customer name]:[Customer name]], '02.MIS Report Table'!$A7, Table1[[Payment Method]:[Payment Method]], "Cash", Table1[[Product]:[Product]], '02.MIS Report Table'!H$6) -> 38911.35 | Q7: =SUMIFS(IF(ISEVEN('07.DRW'!$K$4),INDEX(Table1[],,10),INDEX(Table1[],,11)), Table1[[Customer name]:[Customer name]], '02.MIS Report Table'!$A7, Table1[[Payment Method]:[Payment Method]], "Cash", Table1[[Product]:[Product]], '02.MIS Report Table'!I$6) -> 21100.38 | R7: =SUM(B7:Q7) -> 429926.1
A8: Sneha | B8: =SUMIFS(IF(ISEVEN('07.DRW'!$K$4),INDEX(Table1[],,10),INDEX(Table1[],,11)), Table1[[Customer name]:[Customer name]], '02.MIS Report Table'!$A8, Table1[[Payment Method]:[Payment Method]], "Online", Table1[[Product]:[Product]], '02.MIS Report Table'!B$6) -> 6172.32 | C8: =SUMIFS(IF(ISEVEN('07.DRW'!$K$4),INDEX(Table1[],,10),INDEX(Table1[],,11)), Table1[[Customer name]:[Customer name]], '02.MIS Report Table'!$A8, Table1[[Payment Method]:[Payment Method]], "Online", Table1[[Product]:[Product]], '02.MIS Report Table'!C$6) -> 166184.34 | D8: =SUMIFS(IF(ISEVEN('07.DRW'!$K$4),INDEX(Table1[],,10),INDEX(Table1[],,11)), Table1[[Customer name]:[Customer name]], '02.MIS Report Table'!$A8, Table1[[Payment Method]:[Payment Method]], "Online", Table1[[Product]:[Product]], '02.MIS Report Table'!D$6) -> 340134.79 | E8: =SUMIFS(IF(ISEVEN('07.DRW'!$K$4),INDEX(Table1[],,10),INDEX(Table1[],,11)), Table1[[Customer name]:[Customer name]], '02.MIS Report Table'!$A8, Table1[[Payment Method]:[Payment Method]], "Online", Table1[[Product]:[Product]], '02.MIS Report Table'!E$6) -> 32738 | F8: =SUMIFS(IF(ISEVEN('07.DRW'!$K$4),INDEX(Table1[],,10),INDEX(Table1[],,11)), Table1[[Customer name]:[Customer name]], '02.MIS Report Table'!$A8, Table1[[Payment Method]:[Payment Method]], "Online", Table1[[Product]:[Product]], '02.MIS Report Table'!F$6) -> -10048.36 | G8: =SUMIFS(IF(ISEVEN('07.DRW'!$K$4),INDEX(Table1[],,10),INDEX(Table1[],,11)), Table1[[Customer name]:[Customer name]], '02.MIS Report Table'!$A8, Table1[[Payment Method]:[Payment Method]], "Online", Table1[[Product]:[Product]], '02.MIS Report Table'!G$6) -> 0 | H8: =SUMIFS(IF(ISEVEN('07.DRW'!$K$4),INDEX(Table1[],,10),INDEX(Table1[],,11)), Table1[[Customer name]:[Customer name]], '02.MIS Report Table'!$A8, Table1[[Payment Method]:[Payment Method]], "Online", Table1[[Product]:[Product]], '02.MIS Report Table'!H$6) -> 37795.8 | I8: =SUMIFS(IF(ISEVEN('07.DRW'!$K$4),INDEX(Table1[],,10),INDEX(Table1[],,11)), Table1[[Customer name]:[Customer name]], '02.MIS Report Table'!$A8, Table1[[Payment Method]:[Payment Method]], "Online", Table1[[Product]:[Product]], '02.MIS Report Table'!I$6) -> 7599.84 | J8: =SUMIFS(IF(ISEVEN('07.DRW'!$K$4),INDEX(Table1[],,10),INDEX(Table1[],,11)), Table1[[Customer name]:[Customer name]], '02.MIS Report Table'!$A8, Table1[[Payment Method]:[Payment Method]], "Cash", Table1[[Product]:[Product]], '02.MIS Report Table'!B$6) -> 66475.2 | K8: =SUMIFS(IF(ISEVEN('07.DRW'!$K$4),INDEX(Table1[],,10),INDEX(Table1[],,11)), Table1[[Customer name]:[Customer name]], '02.MIS Report Table'!$A8, Table1[[Payment Method]:[Payment Method]], "Cash", Table1[[Product]:[Product]], '02.MIS Report Table'!C$6) -> 0 | L8: =SUMIFS(IF(ISEVEN('07.DRW'!$K$4),INDEX(Table1[],,10),INDEX(Table1[],,11)), Table1[[Customer name]:[Customer name]], '02.MIS Report Table'!$A8, Table1[[Payment Method]:[Payment Method]], "Cash", Table1[[Product]:[Product]], '02.MIS Report Table'!D$6) -> 71057.36 | M8: =SUMIFS(IF(ISEVEN('07.DRW'!$K$4),INDEX(Table1[],,10),INDEX(Table1[],,11)), Table1[[Customer name]:[Customer name]], '02.MIS Report Table'!$A8, Table1[[Payment Method]:[Payment Method]], "Cash", Table1[[Product]:[Product]], '02.MIS Report Table'!E$6) -> 8229.54 | N8: =SUMIFS(IF(ISEVEN('07.DRW'!$K$4),INDEX(Table1[],,10),INDEX(Table1[],,11)), Table1[[Customer name]:[Customer name]], '02.MIS Report Table'!$A8, Table1[[Payment Method]:[Payment Method]], "Cash", Table1[[Product]:[Product]], '02.MIS Report Table'!F$6) -> 2700.36 | O8: =SUMIFS(IF(ISEVEN('07.DRW'!$K$4),INDEX(Table1[],,10),INDEX(Table1[],,11)), Table1[[Customer name]:[Customer name]], '02.MIS Report Table'!$A8, Table1[[Payment Method]:[Payment Method]], "Cash", Table1[[Product]:[Product]], '02.MIS Report Table'!G$6) -> 0 | P8: =SUMIFS(IF(ISEVEN('07.DRW'!$K$4),INDEX(Table1[],,10),INDEX(Table1[],,11)), Table1[[Customer name]:[Customer name]], '02.MIS Report Table'!$A8, Table1[[Payment Method]:[Payment Method]], "Cash", Table1[[Product]:[Product]], '02.MIS Report Table'!H$6) -> 17982.8 | Q8: =SUMIFS(IF(ISEVEN('07.DRW'!$K$4),INDEX(Table1[],,10),INDEX(Table1[],,11)), Table1[[Customer name]:[Customer name]], '02.MIS Report Table'!$A8, Table1[[Payment Method]:[Payment Method]], "Cash", Table1[[Product]:[Product]], '02.MIS Report Table'!I$6) -> 17868.88 | R8: =SUM(B8:Q8) -> 764890.87
A9: Karan | B9: =SUMIFS(IF(ISEVEN('07.DRW'!$K$4),INDEX(Table1[],,10),INDEX(Table1[],,11)), Table1[[Customer name]:[Customer name]], '02.MIS Report Table'!$A9, Table1[[Payment Method]:[Payment Method]], "Online", Table1[[Product]:[Product]], '02.MIS Report Table'!B$6) -> 56347.9 | C9: =SUMIFS(IF(ISEVEN('07.DRW'!$K$4),INDEX(Table1[],,10),INDEX(Table1[],,11)), Table1[[Customer name]:[Customer name]], '02.MIS Report Table'!$A9, Table1[[Payment Method]:[Payment Method]], "Online", Table1[[Product]:[Product]], '02.MIS Report Table'!C$6) -> 96496.34 | D9: =SUMIFS(IF(ISEVEN('07.DRW'!$K$4),INDEX(Table1[],,10),INDEX(Table1[],,11)), Table1[[Customer name]:[Customer name]], '02.MIS Report Table'!$A9, Table1[[Payment Method]:[Payment Method]], "Online", Table1[[Product]:[Product]], '02.MIS Report Table'!D$6) -> 40117.68 | E9: =SUMIFS(IF(ISEVEN('07.DRW'!$K$4),INDEX(Table1[],,10),INDEX(Table1[],,11)), Table1[[Customer name]:[Customer name]], '02.MIS Report Table'!$A9, Table1[[Payment Method]:[Payment Method]], "Online", Table1[[Product]:[Product]], '02.MIS Report Table'!E$6) -> 106081.18 | F9: =SUMIFS(IF(ISEVEN('07.DRW'!$K$4),INDEX(Table1[],,10),INDEX(Table1[],,11)), Table1[[Customer name]:[Customer name]], '02.MIS Report Table'!$A9, Table1[[Payment Method]:[Payment Method]], "Online", Table1[[Product]:[Product]], '02.MIS Report Table'!F$6) -> 0 | G9: =SUMIFS(IF(ISEVEN('07.DRW'!$K$4),INDEX(Table1[],,10),INDEX(Table1[],,11)), Table1[[Customer name]:[Customer name]], '02.MIS Report Table'!$A9, Table1[[Payment Method]:[Payment Method]], "Online", Table1[[Product]:[Product]], '02.MIS Report Table'!G$6) -> 80402.24 | H9: =SUMIFS(IF(ISEVEN('07.DRW'!$K$4),INDEX(Table1[],,10),INDEX(Table1[],,11)), Table1[[Customer name]:[Customer name]], '02.MIS Report Table'!$A9, Table1[[Payment Method]:[Payment Method]], "Online", Table1[[Product]:[Product]], '02.MIS Report Table'!H$6) -> 46538.24 | I9: =SUMIFS(IF(ISEVEN('07.DRW'!$K$4),INDEX(Table1[],,10),INDEX(Table1[],,11)), Table1[[Customer name]:[Customer name]], '02.MIS Report Table'!$A9, Table1[[Payment Method]:[Payment Method]], "Online", Table1[[Product]:[Product]], '02.MIS Report Table'!I$6) -> 14814 | J9: =SUMIFS(IF(ISEVEN('07.DRW'!$K$4),INDEX(Table1[],,10),INDEX(Table1[],,11)), Table1[[Customer name]:[Customer name]], '02.MIS Report Table'!$A9, Table1[[Payment Method]:[Payment Method]], "Cash", Table1[[Product]:[Product]], '02.MIS Report Table'!B$6) -> 6282.48 | K9: =SUMIFS(IF(ISEVEN('07.DRW'!$K$4),INDEX(Table1[],,10),INDEX(Table1[],,11)), Table1[[Customer name]:[Customer name]], '02.MIS Report Table'!$A9, Table1[[Payment Method]:[Payment Method]], "Cash", Table1[[Product]:[Product]], '02.MIS Report Table'!C$6) -> 6732.3 | L9: =SUMIFS(IF(ISEVEN('07.DRW'!$K$4),INDEX(Table1[],,10),INDEX(Table1[],,11)), Table1[[Customer name]:[Customer name]], '02.MIS Report Table'!$A9, Table1[[Payment Method]:[Payment Method]], "Cash", Table1[[Product]:[Product]], '02.MIS Report Table'!D$6) -> 3573.9 | M9: =SUMIFS(IF(ISEVEN('07.DRW'!$K$4),INDEX(Table1[],,10),INDEX(Table1[],,11)), Table1[[Customer name]:[Customer name]], '02.MIS Report Table'!$A9, Table1[[Payment Method]:[Payment Method]], "Cash", Table1[[Product]:[Product]], '02.MIS Report Table'!E$6) -> 8229.54 | N9: =SUMIFS(IF(ISEVEN('07.DRW'!$K$4),INDEX(Table1[],,10),INDEX(Table1[],,11)), Table1[[Customer name]:[Customer name]], '02.MIS Report Table'!$A9, Table1[[Payment Method]:[Payment Method]], "Cash", Table1[[Product]:[Product]], '02.MIS Report Table'!F$6) -> 84576.7 | O9: =SUMIFS(IF(ISEVEN('07.DRW'!$K$4),INDEX(Table1[],,10),INDEX(Table1[],,11)), Table1[[Customer name]:[Customer name]], '02.MIS Report Table'!$A9, Table1[[Payment Method]:[Payment Method]], "Cash", Table1[[Product]:[Product]], '02.MIS Report Table'!G$6) -> 41560.17 | P9: =SUMIFS(IF(ISEVEN('07.DRW'!$K$4),INDEX(Table1[],,10),INDEX(Table1[],,11)), Table1[[Customer name]:[Customer name]], '02.MIS Report Table'!$A9, Table1[[Payment Method]:[Payment Method]], "Cash", Table1[[Product]:[Product]], '02.MIS Report Table'!H$6) -> 11834.88 | Q9: =SUMIFS(IF(ISEVEN('07.DRW'!$K$4),INDEX(Table1[],,10),INDEX(Table1[],,11)), Table1[[Customer name]:[Customer name]], '02.MIS Report Table'!$A9, Table1[[Payment Method]:[Payment Method]], "Cash", Table1[[Product]:[Product]], '02.MIS Report Table'!I$6) -> 19574.73 | R9: =SUM(B9:Q9) -> 623162.28
A10: Anita | B10: =SUMIFS(IF(ISEVEN('07.DRW'!$K$4),INDEX(Table1[],,10),INDEX(Table1[],,11)), Table1[[Customer name]:[Customer name]], '02.MIS Report Table'!$A10, Table1[[Payment Method]:[Payment Method]], "Online", Table1[[Product]:[Product]], '02.MIS Report Table'!B$6) -> 16305.54 | C10: =SUMIFS(IF(ISEVEN('07.DRW'!$K$4),INDEX(Table1[],,10),INDEX(Table1[],,11)), Table1[[Customer name]:[Customer name]], '02.MIS Report Table'!$A10, Table1[[Payment Method]:[Payment Method]], "Online", Table1[[Product]:[Product]], '02.MIS Report Table'!C$6) -> 16015.32 | D10: =SUMIFS(IF(ISEVEN('07.DRW'!$K$4),INDEX(Table1[],,10),INDEX(Table1[],,11)), Table1[[Customer name]:[Customer name]], '02.MIS Report Table'!$A10, Table1[[Payment Method]:[Payment Method]], "Online", Table1[[Product]:[Product]], '02.MIS Report Table'!D$6) -> 45640.4 | E10: =SUMIFS(IF(ISEVEN('07.DRW'!$K$4),INDEX(Table1[],,10),INDEX(Table1[],,11)), Table1[[Customer name]:[Customer name]], '02.MIS Report Table'!$A10, Table1[[Payment Method]:[Payment Method]], "Online", Table1[[Product]:[Product]], '02.MIS Report Table'!E$6) -> 0 | F10: =SUMIFS(IF(ISEVEN('07.DRW'!$K$4),INDEX(Table1[],,10),INDEX(Table1[],,11)), Table1[[Customer name]:[Customer name]], '02.MIS Report Table'!$A10, Table1[[Payment Method]:[Payment Method]], "Online", Table1[[Product]:[Product]], '02.MIS Report Table'!F$6) -> -146076.88 | G10: =SUMIFS(IF(ISEVEN('07.DRW'!$K$4),INDEX(Table1[],,10),INDEX(Table1[],,11)), Table1[[Customer name]:[Customer name]], '02.MIS Report Table'!$A10, Table1[[Payment Method]:[Payment Method]], "Online", Table1[[Product]:[Product]], '02.MIS Report Table'!G$6) -> 4723.8 | H10: =SUMIFS(IF(ISEVEN('07.DRW'!$K$4),INDEX(Table1[],,10),INDEX(Table1[],,11)), Table1[[Customer name]:[Customer name]], '02.MIS Report Table'!$A10, Table1[[Payment Method]:[Payment Method]], "Online", Table1[[Product]:[Product]], '02.MIS Report Table'!H$6) -> 42364.99 | I10: =SUMIFS(IF(ISEVEN('07.DRW'!$K$4),INDEX(Table1[],,10),INDEX(Table1[],,11)), Table1[[Customer name]:[Customer name]], '02.MIS Report Table'!$A10, Table1[[Payment Method]:[Payment Method]], "Online", Table1[[Product]:[Product]], '02.MIS Report Table'!I$6) -> 11034.4 | J10: =SUMIFS(IF(ISEVEN('07.DRW'!$K$4),INDEX(Table1[],,10),INDEX(Table1[],,11)), Table1[[Customer name]:[Customer name]], '02.MIS Report Table'!$A10, Table1[[Payment Method]:[Payment Method]], "Cash", Table1[[Product]:[Product]], '02.MIS Report Table'!B$6) -> 56696.94 | K10: =SUMIFS(IF(ISEVEN('07.DRW'!$K$4),INDEX(Table1[],,10),INDEX(Table1[],,11)), Table1[[Customer name]:[Customer name]], '02.MIS Report Table'!$A10, Table1[[Payment Method]:[Payment Method]], "Cash", Table1[[Product]:[Product]], '02.MIS Report Table'!C$6) -> 44695.8 | L10: =SUMIFS(IF(ISEVEN('07.DRW'!$K$4),INDEX(Table1[],,10),INDEX(Table1[],,11)), Table1[[Customer name]:[Customer name]], '02.MIS Report Table'!$A10, Table1[[Payment Method]:[Payment Method]], "Cash", Table1[[Product]:[Product]], '02.MIS Report Table'!D$6) -> 10864.02 | M10: =SUMIFS(IF(ISEVEN('07.DRW'!$K$4),INDEX(Table1[],,10),INDEX(Table1[],,11)), Table1[[Customer name]:[Customer name]], '02.MIS Report Table'!$A10, Table1[[Payment Method]:[Payment Method]], "Cash", Table1[[Product]:[Product]], '02.MIS Report Table'!E$6) -> 0 | N10: =SUMIFS(IF(ISEVEN('07.DRW'!$K$4),INDEX(Table1[],,10),INDEX(Table1[],,11)), Table1[[Customer name]:[Customer name]], '02.MIS Report Table'!$A10, Table1[[Payment Method]:[Payment Method]], "Cash", Table1[[Product]:[Product]], '02.MIS Report Table'!F$6) -> 0 | O10: =SUMIFS(IF(ISEVEN('07.DRW'!$K$4),INDEX(Table1[],,10),INDEX(Table1[],,11)), Table1[[Customer name]:[Customer name]], '02.MIS Report Table'!$A10, Table1[[Payment Method]:[Payment Method]], "Cash", Table1[[Product]:[Product]], '02.MIS Report Table'!G$6) -> 54140.4 | P10: =SUMIFS(IF(ISEVEN('07.DRW'!$K$4),INDEX(Table1[],,10),INDEX(Table1[],,11)), Table1[[Customer name]:[Customer name]], '02.MIS Report Table'!$A10, Table1[[Payment Method]:[Payment Method]], "Cash", Table1[[Product]:[Product]], '02.MIS Report Table'!H$6) -> 20765.97 | Q10: =SUMIFS(IF(ISEVEN('07.DRW'!$K$4),INDEX(Table1[],,10),INDEX(Table1[],,11)), Table1[[Customer name]:[Customer name]], '02.MIS Report Table'!$A10, Table1[[Payment Method]:[Payment Method]], "Cash", Table1[[Product]:[Product]], '02.MIS Report Table'!I$6) -> 79311.17 | R10: =SUM(B10:Q10) -> 256481.87
A11: Vikram | B11: =SUMIFS(IF(ISEVEN('07.DRW'!$K$4),INDEX(Table1[],,10),INDEX(Table1[],,11)), Table1[[Customer name]:[Customer name]], '02.MIS Report Table'!$A11, Table1[[Payment Method]:[Payment Method]], "Online", Table1[[Product]:[Product]], '02.MIS Report Table'!B$6) -> 1358.4 | C11: =SUMIFS(IF(ISEVEN('07.DRW'!$K$4),INDEX(Table1[],,10),INDEX(Table1[],,11)), Table1[[Customer name]:[Customer name]], '02.MIS Report Table'!$A11, Table1[[Payment Method]:[Payment Method]], "Online", Table1[[Product]:[Product]], '02.MIS Report Table'!C$6) -> 51955.56 | D11: =SUMIFS(IF(ISEVEN('07.DRW'!$K$4),INDEX(Table1[],,10),INDEX(Table1[],,11)), Table1[[Customer name]:[Customer name]], '02.MIS Report Table'!$A11, Table1[[Payment Method]:[Payment Method]], "Online", Table1[[Product]:[Product]], '02.MIS Report Table'!D$6) -> 12784.2 | E11: =SUMIFS(IF(ISEVEN('07.DRW'!$K$4),INDEX(Table1[],,10),INDEX(Table1[],,11)), Table1[[Customer name]:[Customer name]], '02.MIS Report Table'!$A11, Table1[[Payment Method]:[Payment Method]], "Online", Table1[[Product]:[Product]], '02.MIS Report Table'!E$6) -> 23104.38 | F11: =SUMIFS(IF(ISEVEN('07.DRW'!$K$4),INDEX(Table1[],,10),INDEX(Table1[],,11)), Table1[[Customer name]:[Customer name]], '02.MIS Report Table'!$A11, Table1[[Payment Method]:[Payment Method]], "Online", Table1[[Product]:[Product]], '02.MIS Report Table'!F$6) -> 0 | G11: =SUMIFS(IF(ISEVEN('07.DRW'!$K$4),INDEX(Table1[],,10),INDEX(Table1[],,11)), Table1[[Customer name]:[Customer name]], '02.MIS Report Table'!$A11, Table1[[Payment Method]:[Payment Method]], "Online", Table1[[Product]:[Product]], '02.MIS Report Table'!G$6) -> 10406.14 | H11: =SUMIFS(IF(ISEVEN('07.DRW'!$K$4),INDEX(Table1[],,10),INDEX(Table1[],,11)), Table1[[Customer name]:[Customer name]], '02.MIS Report Table'!$A11, Table1[[Payment Method]:[Payment Method]], "Online", Table1[[Product]:[Product]], '02.MIS Report Table'!H$6) -> 0 | I11: =SUMIFS(IF(ISEVEN('07.DRW'!$K$4),INDEX(Table1[],,10),INDEX(Table1[],,11)), Table1[[Customer name]:[Customer name]], '02.MIS Report Table'!$A11, Table1[[Payment Method]:[Payment Method]], "Online", Table1[[Product]:[Product]], '02.MIS Report Table'!I$6) -> 24613.8 | J11: =SUMIFS(IF(ISEVEN('07.DRW'!$K$4),INDEX(Table1[],,10),INDEX(Table1[],,11)), Table1[[Customer name]:[Customer name]], '02.MIS Report Table'!$A11, Table1[[Payment Method]:[Payment Method]], "Cash", Table1[[Product]:[Product]], '02.MIS Report Table'!B$6) -> 56657.77 | K11: =SUMIFS(IF(ISEVEN('07.DRW'!$K$4),INDEX(Table1[],,10),INDEX(Table1[],,11)), Table1[[Customer name]:[Customer name]], '02.MIS Report Table'!$A11, Table1[[Payment Method]:[Payment Method]], "Cash", Table1[[Product]:[Product]], '02.MIS Report Table'!C$6) -> 59876.46 | L11: =SUMIFS(IF(ISEVEN('07.DRW'!$K$4),INDEX(Table1[],,10),INDEX(Table1[],,11)), Table1[[Customer name]:[Customer name]], '02.MIS Report Table'!$A11, Table1[[Payment Method]:[Payment Method]], "Cash", Table1[[Product]:[Product]], '02.MIS Report Table'!D$6) -> 35378.2 | M11: =SUMIFS(IF(ISEVEN('07.DRW'!$K$4),INDEX(Table1[],,10),INDEX(Table1[],,11)), Table1[[Customer name]:[Customer name]], '02.MIS Report Table'!$A11, Table1[[Payment Method]:[Payment Method]], "Cash", Table1[[Product]:[Product]], '02.MIS Report Table'!E$6) -> 63620.46 | N11: =SUMIFS(IF(ISEVEN('07.DRW'!$K$4),INDEX(Table1[],,10),INDEX(Table1[],,11)), Table1[[Customer name]:[Customer name]], '02.MIS Report Table'!$A11, Table1[[Payment Method]:[Payment Method]], "Cash", Table1[[Product]:[Product]], '02.MIS Report Table'!F$6) -> 64312.37 | O11: =SUMIFS(IF(ISEVEN('07.DRW'!$K$4),INDEX(Table1[],,10),INDEX(Table1[],,11)), Table1[[Customer name]:[Customer name]], '02.MIS Report Table'!$A11, Table1[[Payment Method]:[Payment Method]], "Cash", Table1[[Product]:[Product]], '02.MIS Report Table'!G$6) -> 0 | P11: =SUMIFS(IF(ISEVEN('07.DRW'!$K$4),INDEX(Table1[],,10),INDEX(Table1[],,11)), Table1[[Customer name]:[Customer name]], '02.MIS Report Table'!$A11, Table1[[Payment Method]:[Payment Method]], "Cash", Table1[[Product]:[Product]], '02.MIS Report Table'!H$6) -> 83827.4 | Q11: =SUMIFS(IF(ISEVEN('07.DRW'!$K$4),INDEX(Table1[],,10),INDEX(Table1[],,11)), Table1[[Customer name]:[Customer name]], '02.MIS Report Table'!$A11, Table1[[Payment Method]:[Payment Method]], "Cash", Table1[[Product]:[Product]], '02.MIS Report Table'!I$6) -> 40377.6 | R11: =SUM(B11:Q11) -> 528272.74
A12: Sneha Gupta | B12: =SUMIFS(IF(ISEVEN('07.DRW'!$K$4),INDEX(Table1[],,10),INDEX(Table1[],,11)), Table1[[Customer name]:[Customer name]], '02.MIS Report Table'!$A12, Table1[[Payment Method]:[Payment Method]], "Online", Table1[[Product]:[Product]], '02.MIS Report Table'!B$6) -> 0 | C12: =SUMIFS(IF(ISEVEN('07.DRW'!$K$4),INDEX(Table1[],,10),INDEX(Table1[],,11)), Table1[[Customer name]:[Customer name]], '02.MIS Report Table'!$A12, Table1[[Payment Method]:[Payment Method]], "Online", Table1[[Product]:[Product]], '02.MIS Report Table'!C$6) -> 0 | D12: =SUMIFS(IF(ISEVEN('07.DRW'!$K$4),INDEX(Table1[],,10),INDEX(Table1[],,11)), Table1[[Customer name]:[Customer name]], '02.MIS Report Table'!$A12, Table1[[Payment Method]:[Payment Method]], "Online", Table1[[Product]:[Product]], '02.MIS Report Table'!D$6) -> -125827.64 | E12: =SUMIFS(IF(ISEVEN('07.DRW'!$K$4),INDEX(Table1[],,10),INDEX(Table1[],,11)), Table1[[Customer name]:[Customer name]], '02.MIS Report Table'!$A12, Table1[[Payment Method]:[Payment Method]], "Online", Table1[[Product]:[Product]], '02.MIS Report Table'!E$6) -> 14070.56 | F12: =SUMIFS(IF(ISEVEN('07.DRW'!$K$4),INDEX(Table1[],,10),INDEX(Table1[],,11)), Table1[[Customer name]:[Customer name]], '02.MIS Report Table'!$A12, Table1[[Payment Method]:[Payment Method]], "Online", Table1[[Product]:[Product]], '02.MIS Report Table'!F$6) -> 35842.56 | G12: =SUMIFS(IF(ISEVEN('07.DRW'!$K$4),INDEX(Table1[],,10),INDEX(Table1[],,11)), Table1[[Customer name]:[Customer name]], '02.MIS Report Table'!$A12, Table1[[Payment Method]:[Payment Method]], "Online", Table1[[Product]:[Product]], '02.MIS Report Table'!G$6) -> 42988.52 | H12: =SUMIFS(IF(ISEVEN('07.DRW'!$K$4),INDEX(Table1[],,10),INDEX(Table1[],,11)), Table1[[Customer name]:[Customer name]], '02.MIS Report Table'!$A12, Table1[[Payment Method]:[Payment Method]], "Online", Table1[[Product]:[Product]], '02.MIS Report Table'!H$6) -> 0 | I12: =SUMIFS(IF(ISEVEN('07.DRW'!$K$4),INDEX(Table1[],,10),INDEX(Table1[],,11)), Table1[[Customer name]:[Customer name]], '02.MIS Report Table'!$A12, Table1[[Payment Method]:[Payment Method]], "Online", Table1[[Product]:[Product]], '02.MIS Report Table'!I$6) -> 0 | J12: =SUMIFS(IF(ISEVEN('07.DRW'!$K$4),INDEX(Table1[],,10),INDEX(Table1[],,11)), Table1[[Customer name]:[Customer name]], '02.MIS Report Table'!$A12, Table1[[Payment Method]:[Payment Method]], "Cash", Table1[[Product]:[Product]], '02.MIS Report Table'!B$6) -> 65452.8 | K12: =SUMIFS(IF(ISEVEN('07.DRW'!$K$4),INDEX(Table1[],,10),INDEX(Table1[],,11)), Table1[[Customer name]:[Customer name]], '02.MIS Report Table'!$A12, Table1[[Payment Method]:[Payment Method]], "Cash", Table1[[Product]:[Product]], '02.MIS Report Table'!C$6) -> 19951.68 | L12: =SUMIFS(IF(ISEVEN('07.DRW'!$K$4),INDEX(Table1[],,10),INDEX(Table1[],,11)), Table1[[Customer name]:[Customer name]], '02.MIS Report Table'!$A12, Table1[[Payment Method]:[Payment Method]], "Cash", Table1[[Product]:[Product]], '02.MIS Report Table'!D$6) -> 0 | M12: =SUMIFS(IF(ISEVEN('07.DRW'!$K$4),INDEX(Table1[],,10),INDEX(Table1[],,11)), Table1[[Customer name]:[Customer name]], '02.MIS Report Table'!$A12, Table1[[Payment Method]:[Payment Method]], "Cash", Table1[[Product]:[Product]], '02.MIS Report Table'!E$6) -> 17991 | N12: =SUMIFS(IF(ISEVEN('07.DRW'!$K$4),INDEX(Table1[],,10),INDEX(Table1[],,11)), Table1[[Customer name]:[Customer name]], '02.MIS Report Table'!$A12, Table1[[Payment Method]:[Payment Method]], "Cash", Table1[[Product]:[Product]], '02.MIS Report Table'!F$6) -> 4420.08 | O12: =SUMIFS(IF(ISEVEN('07.DRW'!$K$4),INDEX(Table1[],,10),INDEX(Table1[],,11)), Table1[[Customer name]:[Customer name]], '02.MIS Report Table'!$A12, Table1[[Payment Method]:[Payment Method]], "Cash", Table1[[Product]:[Product]], '02.MIS Report Table'!G$6) -> 0 | P12: =SUMIFS(IF(ISEVEN('07.DRW'!$K$4),INDEX(Table1[],,10),INDEX(Table1[],,11)), Table1[[Customer name]:[Customer name]], '02.MIS Report Table'!$A12, Table1[[Payment Method]:[Payment Method]], "Cash", Table1[[Product]:[Product]], '02.MIS Report Table'!H$6) -> 0 | Q12: =SUMIFS(IF(ISEVEN('07.DRW'!$K$4),INDEX(Table1[],,10),INDEX(Table1[],,11)), Table1[[Customer name]:[Customer name]], '02.MIS Report Table'!$A12, Table1[[Payment Method]:[Payment Method]], "Cash", Table1[[Product]:[Product]], '02.MIS Report Table'!I$6) -> 43898.56 | R12: =SUM(B12:Q12) -> 118788.12
A13: Rahul | B13: =SUMIFS(IF(ISEVEN('07.DRW'!$K$4),INDEX(Table1[],,10),INDEX(Table1[],,11)), Table1[[Customer name]:[Customer name]], '02.MIS Report Table'!$A13, Table1[[Payment Method]:[Payment Method]], "Online", Table1[[Product]:[Product]], '02.MIS Report Table'!B$6) -> 12882.66 | C13: =SUMIFS(IF(ISEVEN('07.DRW'!$K$4),INDEX(Table1[],,10),INDEX(Table1[],,11)), Table1[[Customer name]:[Customer name]], '02.MIS Report Table'!$A13, Table1[[Payment Method]:[Payment Method]], "Online", Table1[[Product]:[Product]], '02.MIS Report Table'!C$6) -> 158461.84 | D13: =SUMIFS(IF(ISEVEN('07.DRW'!$K$4),INDEX(Table1[],,10),INDEX(Table1[],,11)), Table1[[Customer name]:[Customer name]], '02.MIS Report Table'!$A13, Table1[[Payment Method]:[Payment Method]], "Online", Table1[[Product]:[Product]], '02.MIS Report Table'!D$6) -> 28338.3 | E13: =SUMIFS(IF(ISEVEN('07.DRW'!$K$4),INDEX(Table1[],,10),INDEX(Table1[],,11)), Table1[[Customer name]:[Customer name]], '02.MIS Report Table'!$A13, Table1[[Payment Method]:[Payment Method]], "Online", Table1[[Product]:[Product]], '02.MIS Report Table'!E$6) -> 53662.6 | F13: =SUMIFS(IF(ISEVEN('07.DRW'!$K$4),INDEX(Table1[],,10),INDEX(Table1[],,11)), Table1[[Customer name]:[Customer name]], '02.MIS Report Table'!$A13, Table1[[Payment Method]:[Payment Method]], "Online", Table1[[Product]:[Product]], '02.MIS Report Table'!F$6) -> 24453.44 | G13: =SUMIFS(IF(ISEVEN('07.DRW'!$K$4),INDEX(Table1[],,10),INDEX(Table1[],,11)), Table1[[Customer name]:[Customer name]], '02.MIS Report Table'!$A13, Table1[[Payment Method]:[Payment Method]], "Online", Table1[[Product]:[Product]], '02.MIS Report Table'!G$6) -> 16921.92 | H13: =SUMIFS(IF(ISEVEN('07.DRW'!$K$4),INDEX(Table1[],,10),INDEX(Table1[],,11)), Table1[[Customer name]:[Customer name]], '02.MIS Report Table'!$A13, Table1[[Payment Method]:[Payment Method]], "Online", Table1[[Product]:[Product]], '02.MIS Report Table'!H$6) -> 22594.07 | I13: =SUMIFS(IF(ISEVEN('07.DRW'!$K$4),INDEX(Table1[],,10),INDEX(Table1[],,11)), Table1[[Customer name]:[Customer name]], '02.MIS Report Table'!$A13, Table1[[Payment Method]:[Payment Method]], "Online", Table1[[Product]:[Product]], '02.MIS Report Table'!I$6) -> 17298.6 | J13: =SUMIFS(IF(ISEVEN('07.DRW'!$K$4),INDEX(Table1[],,10),INDEX(Table1[],,11)), Table1[[Customer name]:[Customer name]], '02.MIS Report Table'!$A13, Table1[[Payment Method]:[Payment Method]], "Cash", Table1[[Product]:[Product]], '02.MIS Report Table'!B$6) -> 61923.34 | K13: =SUMIFS(IF(ISEVEN('07.DRW'!$K$4),INDEX(Table1[],,10),INDEX(Table1[],,11)), Table1[[Customer name]:[Customer name]], '02.MIS Report Table'!$A13, Table1[[Payment Method]:[Payment Method]], "Cash", Table1[[Product]:[Product]], '02.MIS Report Table'!C$6) -> 45139.36 | L13: =SUMIFS(IF(ISEVEN('07.DRW'!$K$4),INDEX(Table1[],,10),INDEX(Table1[],,11)), Table1[[Customer name]:[Customer name]], '02.MIS Report Table'!$A13, Table1[[Payment Method]:[Payment Method]], "Cash", Table1[[Product]:[Product]], '02.MIS Report Table'!D$6) -> 43792.56 | M13: =SUMIFS(IF(ISEVEN('07.DRW'!$K$4),INDEX(Table1[],,10),INDEX(Table1[],,11)), Table1[[Customer name]:[Customer name]], '02.MIS Report Table'!$A13, Table1[[Payment Method]:[Payment Method]], "Cash", Table1[[Product]:[Product]], '02.MIS Report Table'!E$6) -> 68628.78 | N13: =SUMIFS(IF(ISEVEN('07.DRW'!$K$4),INDEX(Table1[],,10),INDEX(Table1[],,11)), Table1[[Customer name]:[Customer name]], '02.MIS Report Table'!$A13, Table1[[Payment Method]:[Payment Method]], "Cash", Table1[[Product]:[Product]], '02.MIS Report Table'!F$6) -> 41369.66 | O13: =SUMIFS(IF(ISEVEN('07.DRW'!$K$4),INDEX(Table1[],,10),INDEX(Table1[],,11)), Table1[[Customer name]:[Customer name]], '02.MIS Report Table'!$A13, Table1[[Payment Method]:[Payment Method]], "Cash", Table1[[Product]:[Product]], '02.MIS Report Table'!G$6) -> 59989.85 | P13: =SUMIFS(IF(ISEVEN('07.DRW'!$K$4),INDEX(Table1[],,10),INDEX(Table1[],,11)), Table1[[Customer name]:[Customer name]], '02.MIS Report Table'!$A13, Table1[[Payment Method]:[Payment Method]], "Cash", Table1[[Product]:[Product]], '02.MIS Report Table'!H$6) -> 15200 | Q13: =SUMIFS(IF(ISEVEN('07.DRW'!$K$4),INDEX(Table1[],,10),INDEX(Table1[],,11)), Table1[[Customer name]:[Customer name]], '02.MIS Report Table'!$A13, Table1[[Payment Method]:[Payment Method]], "Cash", Table1[[Product]:[Product]], '02.MIS Report Table'!I$6) -> 20838.36 | R13: =SUM(B13:Q13) -> 691495.34
A14: Shivam | B14: =SUMIFS(IF(ISEVEN('07.DRW'!$K$4),INDEX(Table1[],,10),INDEX(Table1[],,11)), Table1[[Customer name]:[Customer name]], '02.MIS Report Table'!$A14, Table1[[Payment Method]:[Payment Method]], "Online", Table1[[Product]:[Product]], '02.MIS Report Table'!B$6) -> 41775.6 | C14: =SUMIFS(IF(ISEVEN('07.DRW'!$K$4),INDEX(Table1[],,10),INDEX(Table1[],,11)), Table1[[Customer name]:[Customer name]], '02.MIS Report Table'!$A14, Table1[[Payment Method]:[Payment Method]], "Online", Table1[[Product]:[Product]], '02.MIS Report Table'!C$6) -> 40856.4 | D14: =SUMIFS(IF(ISEVEN('07.DRW'!$K$4),INDEX(Table1[],,10),INDEX(Table1[],,11)), Table1[[Customer name]:[Customer name]], '02.MIS Report Table'!$A14, Table1[[Payment Method]:[Payment Method]], "Online", Table1[[Product]:[Product]], '02.MIS Report Table'!D$6) -> 37059.12 | E14: =SUMIFS(IF(ISEVEN('07.DRW'!$K$4),INDEX(Table1[],,10),INDEX(Table1[],,11)), Table1[[Customer name]:[Customer name]], '02.MIS Report Table'!$A14, Table1[[Payment Method]:[Payment Method]], "Online", Table1[[Product]:[Product]], '02.MIS Report Table'!E$6) -> 0 | F14: =SUMIFS(IF(ISEVEN('07.DRW'!$K$4),INDEX(Table1[],,10),INDEX(Table1[],,11)), Table1[[Customer name]:[Customer name]], '02.MIS Report Table'!$A14, Table1[[Payment Method]:[Payment Method]], "Online", Table1[[Product]:[Product]], '02.MIS Report Table'!F$6) -> 34743.6 | G14: =SUMIFS(IF(ISEVEN('07.DRW'!$K$4),INDEX(Table1[],,10),INDEX(Table1[],,11)), Table1[[Customer name]:[Customer name]], '02.MIS Report Table'!$A14, Table1[[Payment Method]:[Payment Method]], "Online", Table1[[Product]:[Product]], '02.MIS Report Table'!G$6) -> 63330.22 | H14: =SUMIFS(IF(ISEVEN('07.DRW'!$K$4),INDEX(Table1[],,10),INDEX(Table1[],,11)), Table1[[Customer name]:[Customer name]], '02.MIS Report Table'!$A14, Table1[[Payment Method]:[Payment Method]], "Online", Table1[[Product]:[Product]], '02.MIS Report Table'!H$6) -> 75013.1 | I14: =SUMIFS(IF(ISEVEN('07.DRW'!$K$4),INDEX(Table1[],,10),INDEX(Table1[],,11)), Table1[[Customer name]:[Customer name]], '02.MIS Report Table'!$A14, Table1[[Payment Method]:[Payment Method]], "Online", Table1[[Product]:[Product]], '02.MIS Report Table'!I$6) -> 141693.16 | J14: =SUMIFS(IF(ISEVEN('07.DRW'!$K$4),INDEX(Table1[],,10),INDEX(Table1[],,11)), Table1[[Customer name]:[Customer name]], '02.MIS Report Table'!$A14, Table1[[Payment Method]:[Payment Method]], "Cash", Table1[[Product]:[Product]], '02.MIS Report Table'!B$6) -> 0 | K14: =SUMIFS(IF(ISEVEN('07.DRW'!$K$4),INDEX(Table1[],,10),INDEX(Table1[],,11)), Table1[[Customer name]:[Customer name]], '02.MIS Report Table'!$A14, Table1[[Payment Method]:[Payment Method]], "Cash", Table1[[Product]:[Product]], '02.MIS Report Table'!C$6) -> 87674.85 | L14: =SUMIFS(IF(ISEVEN('07.DRW'!$K$4),INDEX(Table1[],,10),INDEX(Table1[],,11)), Table1[[Customer name]:[Customer name]], '02.MIS Report Table'!$A14, Table1[[Payment Method]:[Payment Method]], "Cash", Table1[[Product]:[Product]], '02.MIS Report Table'!D$6) -> 7242 | M14: =SUMIFS(IF(ISEVEN('07.DRW'!$K$4),INDEX(Table1[],,10),INDEX(Table1[],,11)), Table1[[Customer name]:[Customer name]], '02.MIS Report Table'!$A14, Table1[[Payment Method]:[Payment Method]], "Cash", Table1[[Product]:[Product]], '02.MIS Report Table'!E$6) -> 29282.5 | N14: =SUMIFS(IF(ISEVEN('07.DRW'!$K$4),INDEX(Table1[],,10),INDEX(Table1[],,11)), Table1[[Customer name]:[Customer name]], '02.MIS Report Table'!$A14, Table1[[Payment Method]:[Payment Method]], "Cash", Table1[[Product]:[Product]], '02.MIS Report Table'!F$6) -> 75707.28 | O14: =SUMIFS(IF(ISEVEN('07.DRW'!$K$4),INDEX(Table1[],,10),INDEX(Table1[],,11)), Table1[[Customer name]:[Customer name]], '02.MIS Report Table'!$A14, Table1[[Payment Method]:[Payment Method]], "Cash", Table1[[Product]:[Product]], '02.MIS Report Table'!G$6) -> 36925.32 | P14: =SUMIFS(IF(ISEVEN('07.DRW'!$K$4),INDEX(Table1[],,10),INDEX(Table1[],,11)), Table1[[Customer name]:[Customer name]], '02.MIS Report Table'!$A14, Table1[[Payment Method]:[Payment Method]], "Cash", Table1[[Product]:[Product]], '02.MIS Report Table'!H$6) -> 55295.46 | Q14: =SUMIFS(IF(ISEVEN('07.DRW'!$K$4),INDEX(Table1[],,10),INDEX(Table1[],,11)), Table1[[Customer name]:[Customer name]], '02.MIS Report Table'!$A14, Table1[[Payment Method]:[Payment Method]], "Cash", Table1[[Product]:[Product]], '02.MIS Report Table'!I$6) -> 11021.76 | R14: =SUM(B14:Q14) -> 737620.37
A15: Pooja | B15: =SUMIFS(IF(ISEVEN('07.DRW'!$K$4),INDEX(Table1[],,10),INDEX(Table1[],,11)), Table1[[Customer name]:[Customer name]], '02.MIS Report Table'!$A15, Table1[[Payment Method]:[Payment Method]], "Online", Table1[[Product]:[Product]], '02.MIS Report Table'!B$6) -> 24816 | C15: =SUMIFS(IF(ISEVEN('07.DRW'!$K$4),INDEX(Table1[],,10),INDEX(Table1[],,11)), Table1[[Customer name]:[Customer name]], '02.MIS Report Table'!$A15, Table1[[Payment Method]:[Payment Method]], "Online", Table1[[Product]:[Product]], '02.MIS Report Table'!C$6) -> 8816.22 | D15: =SUMIFS(IF(ISEVEN('07.DRW'!$K$4),INDEX(Table1[],,10),INDEX(Table1[],,11)), Table1[[Customer name]:[Customer name]], '02.MIS Report Table'!$A15, Table1[[Payment Method]:[Payment Method]], "Online", Table1[[Product]:[Product]], '02.MIS Report Table'!D$6) -> 50726.56 | E15: =SUMIFS(IF(ISEVEN('07.DRW'!$K$4),INDEX(Table1[],,10),INDEX(Table1[],,11)), Table1[[Customer name]:[Customer name]], '02.MIS Report Table'!$A15, Table1[[Payment Method]:[Payment Method]], "Online", Table1[[Product]:[Product]], '02.MIS Report Table'!E$6) -> 42223.43 | F15: =SUMIFS(IF(ISEVEN('07.DRW'!$K$4),INDEX(Table1[],,10),INDEX(Table1[],,11)), Table1[[Customer name]:[Customer name]], '02.MIS Report Table'!$A15, Table1[[Payment Method]:[Payment Method]], "Online", Table1[[Product]:[Product]], '02.MIS Report Table'!F$6) -> 25167.33 | G15: =SUMIFS(IF(ISEVEN('07.DRW'!$K$4),INDEX(Table1[],,10),INDEX(Table1[],,11)), Table1[[Customer name]:[Customer name]], '02.MIS Report Table'!$A15, Table1[[Payment Method]:[Payment Method]], "Online", Table1[[Product]:[Product]], '02.MIS Report Table'!G$6) -> 29157.72 | H15: =SUMIFS(IF(ISEVEN('07.DRW'!$K$4),INDEX(Table1[],,10),INDEX(Table1[],,11)), Table1[[Customer name]:[Customer name]], '02.MIS Report Table'!$A15, Table1[[Payment Method]:[Payment Method]], "Online", Table1[[Product]:[Product]], '02.MIS Report Table'!H$6) -> 13886.52 | I15: =SUMIFS(IF(ISEVEN('07.DRW'!$K$4),INDEX(Table1[],,10),INDEX(Table1[],,11)), Table1[[Customer name]:[Customer name]], '02.MIS Report Table'!$A15, Table1[[Payment Method]:[Payment Method]], "Online", Table1[[Product]:[Product]], '02.MIS Report Table'!I$6) -> 48716.27 | J15: =SUMIFS(IF(ISEVEN('07.DRW'!$K$4),INDEX(Table1[],,10),INDEX(Table1[],,11)), Table1[[Customer name]:[Customer name]], '02.MIS Report Table'!$A15, Table1[[Payment Method]:[Payment Method]], "Cash", Table1[[Product]:[Product]], '02.MIS Report Table'!B$6) -> 0 | K15: =SUMIFS(IF(ISEVEN('07.DRW'!$K$4),INDEX(Table1[],,10),INDEX(Table1[],,11)), Table1[[Customer name]:[Customer name]], '02.MIS Report Table'!$A15, Table1[[Payment Method]:[Payment Method]], "Cash", Table1[[Product]:[Product]], '02.MIS Report Table'!C$6) -> 37027.2 | L15: =SUMIFS(IF(ISEVEN('07.DRW'!$K$4),INDEX(Table1[],,10),INDEX(Table1[],,11)), Table1[[Customer name]:[Customer name]], '02.MIS Report Table'!$A15, Table1[[Payment Method]:[Payment Method]], "Cash", Table1[[Product]:[Product]], '02.MIS Report Table'!D$6) -> 23950.62 | M15: =SUMIFS(IF(ISEVEN('07.DRW'!$K$4),INDEX(Table1[],,10),INDEX(Table1[],,11)), Table1[[Customer name]:[Customer name]], '02.MIS Report Table'!$A15, Table1[[Payment Method]:[Payment Method]], "Cash", Table1[[Product]:[Product]], '02.MIS Report Table'!E$6) -> 28551.75 | N15: =SUMIFS(IF(ISEVEN('07.DRW'!$K$4),INDEX(Table1[],,10),INDEX(Table1[],,11)), Table1[[Customer name]:[Customer name]], '02.MIS Report Table'!$A15, Table1[[Payment Method]:[Payment Method]], "Cash", Table1[[Product]:[Product]], '02.MIS Report Table'!F$6) -> 24453.44 | O15: =SUMIFS(IF(ISEVEN('07.DRW'!$K$4),INDEX(Table1[],,10),INDEX(Table1[],,11)), Table1[[Customer name]:[Customer name]], '02.MIS Report Table'!$A15, Table1[[Payment Method]:[Payment Method]], "Cash", Table1[[Product]:[Product]], '02.MIS Report Table'!G$6) -> 57698.52 | P15: =SUMIFS(IF(ISEVEN('07.DRW'!$K$4),INDEX(Table1[],,10),INDEX(Table1[],,11)), Table1[[Customer name]:[Customer name]], '02.MIS Report Table'!$A15, Table1[[Payment Method]:[Payment Method]], "Cash", Table1[[Product]:[Product]], '02.MIS Report Table'!H$6) -> 69422.88 | Q15: =SUMIFS(IF(ISEVEN('07.DRW'!$K$4),INDEX(Table1[],,10),INDEX(Table1[],,11)), Table1[[Customer name]:[Customer name]], '02.MIS Report Table'!$A15, Table1[[Payment Method]:[Payment Method]], "Cash", Table1[[Product]:[Product]], '02.MIS Report Table'!I$6) -> 0 | R15: =SUM(B15:Q15) -> 484614.46
A16: Priya Gupta | B16: =SUMIFS(IF(ISEVEN('07.DRW'!$K$4),INDEX(Table1[],,10),INDEX(Table1[],,11)), Table1[[Customer name]:[Customer name]], '02.MIS Report Table'!$A16, Table1[[Payment Method]:[Payment Method]], "Online", Table1[[Product]:[Product]], '02.MIS Report Table'!B$6) -> 87732.23 | C16: =SUMIFS(IF(ISEVEN('07.DRW'!$K$4),INDEX(Table1[],,10),INDEX(Table1[],,11)), Table1[[Customer name]:[Customer name]], '02.MIS Report Table'!$A16, Table1[[Payment Method]:[Payment Method]], "Online", Table1[[Product]:[Product]], '02.MIS Report Table'!C$6) -> 0 | D16: =SUMIFS(IF(ISEVEN('07.DRW'!$K$4),INDEX(Table1[],,10),INDEX(Table1[],,11)), Table1[[Customer name]:[Customer name]], '02.MIS Report Table'!$A16, Table1[[Payment Method]:[Payment Method]], "Online", Table1[[Product]:[Product]], '02.MIS Report Table'!D$6) -> 65225.8 | E16: =SUMIFS(IF(ISEVEN('07.DRW'!$K$4),INDEX(Table1[],,10),INDEX(Table1[],,11)), Table1[[Customer name]:[Customer name]], '02.MIS Report Table'!$A16, Table1[[Payment Method]:[Payment Method]], "Online", Table1[[Product]:[Product]], '02.MIS Report Table'!E$6) -> 19211.53 | F16: =SUMIFS(IF(ISEVEN('07.DRW'!$K$4),INDEX(Table1[],,10),INDEX(Table1[],,11)), Table1[[Customer name]:[Customer name]], '02.MIS Report Table'!$A16, Table1[[Payment Method]:[Payment Method]], "Online", Table1[[Product]:[Product]], '02.MIS Report Table'!F$6) -> 66184.64 | G16: =SUMIFS(IF(ISEVEN('07.DRW'!$K$4),INDEX(Table1[],,10),INDEX(Table1[],,11)), Table1[[Customer name]:[Customer name]], '02.MIS Report Table'!$A16, Table1[[Payment Method]:[Payment Method]], "Online", Table1[[Product]:[Product]], '02.MIS Report Table'!G$6) -> 87304.2 | H16: =SUMIFS(IF(ISEVEN('07.DRW'!$K$4),INDEX(Table1[],,10),INDEX(Table1[],,11)), Table1[[Customer name]:[Customer name]], '02.MIS Report Table'!$A16, Table1[[Payment Method]:[Payment Method]], "Online", Table1[[Product]:[Product]], '02.MIS Report Table'!H$6) -> 2076.84 | I16: =SUMIFS(IF(ISEVEN('07.DRW'!$K$4),INDEX(Table1[],,10),INDEX(Table1[],,11)), Table1[[Customer name]:[Customer name]], '02.MIS Report Table'!$A16, Table1[[Payment Method]:[Payment Method]], "Online", Table1[[Product]:[Product]], '02.MIS Report Table'!I$6) -> 48710.49 | J16: =SUMIFS(IF(ISEVEN('07.DRW'!$K$4),INDEX(Table1[],,10),INDEX(Table1[],,11)), Table1[[Customer name]:[Customer name]], '02.MIS Report Table'!$A16, Table1[[Payment Method]:[Payment Method]], "Cash", Table1[[Product]:[Product]], '02.MIS Report Table'!B$6) -> 22470 | K16: =SUMIFS(IF(ISEVEN('07.DRW'!$K$4),INDEX(Table1[],,10),INDEX(Table1[],,11)), Table1[[Customer name]:[Customer name]], '02.MIS Report Table'!$A16, Table1[[Payment Method]:[Payment Method]], "Cash", Table1[[Product]:[Product]], '02.MIS Report Table'!C$6) -> 21572.6 | L16: =SUMIFS(IF(ISEVEN('07.DRW'!$K$4),INDEX(Table1[],,10),INDEX(Table1[],,11)), Table1[[Customer name]:[Customer name]], '02.MIS Report Table'!$A16, Table1[[Payment Method]:[Payment Method]], "Cash", Table1[[Product]:[Product]], '02.MIS Report Table'!D$6) -> 0 | M16: =SUMIFS(IF(ISEVEN('07.DRW'!$K$4),INDEX(Table1[],,10),INDEX(Table1[],,11)), Table1[[Customer name]:[Customer name]], '02.MIS Report Table'!$A16, Table1[[Payment Method]:[Payment Method]], "Cash", Table1[[Product]:[Product]], '02.MIS Report Table'!E$6) -> 0 | N16: =SUMIFS(IF(ISEVEN('07.DRW'!$K$4),INDEX(Table1[],,10),INDEX(Table1[],,11)), Table1[[Customer name]:[Customer name]], '02.MIS Report Table'!$A16, Table1[[Payment Method]:[Payment Method]], "Cash", Table1[[Product]:[Product]], '02.MIS Report Table'!F$6) -> 113797.68 | O16: =SUMIFS(IF(ISEVEN('07.DRW'!$K$4),INDEX(Table1[],,10),INDEX(Table1[],,11)), Table1[[Customer name]:[Customer name]], '02.MIS Report Table'!$A16, Table1[[Payment Method]:[Payment Method]], "Cash", Table1[[Product]:[Product]], '02.MIS Report Table'!G$6) -> 10754.1 | P16: =SUMIFS(IF(ISEVEN('07.DRW'!$K$4),INDEX(Table1[],,10),INDEX(Table1[],,11)), Table1[[Customer name]:[Customer name]], '02.MIS Report Table'!$A16, Table1[[Payment Method]:[Payment Method]], "Cash", Table1[[Product]:[Product]], '02.MIS Report Table'!H$6) -> 0 | Q16: =SUMIFS(IF(ISEVEN('07.DRW'!$K$4),INDEX(Table1[],,10),INDEX(Table1[],,11)), Table1[[Customer name]:[Customer name]], '02.MIS Report Table'!$A16, Table1[[Payment Method]:[Payment Method]], "Cash", Table1[[Product]:[Product]], '02.MIS Report Table'!I$6) -> 58108.81 | R16: =SUM(B16:Q16) -> 603148.92
A17: Priya | B17: =SUMIFS(IF(ISEVEN('07.DRW'!$K$4),INDEX(Table1[],,10),INDEX(Table1[],,11)), Table1[[Customer name]:[Customer name]], '02.MIS Report Table'!$A17, Table1[[Payment Method]:[Payment Method]], "Online", Table1[[Product]:[Product]], '02.MIS Report Table'!B$6) -> 100613.95 | C17: =SUMIFS(IF(ISEVEN('07.DRW'!$K$4),INDEX(Table1[],,10),INDEX(Table1[],,11)), Table1[[Customer name]:[Customer name]], '02.MIS Report Table'!$A17, Table1[[Payment Method]:[Payment Method]], "Online", Table1[[Product]:[Product]], '02.MIS Report Table'!C$6) -> 19789.77 | D17: =SUMIFS(IF(ISEVEN('07.DRW'!$K$4),INDEX(Table1[],,10),INDEX(Table1[],,11)), Table1[[Customer name]:[Customer name]], '02.MIS Report Table'!$A17, Table1[[Payment Method]:[Payment Method]], "Online", Table1[[Product]:[Product]], '02.MIS Report Table'!D$6) -> 31183.04 | E17: =SUMIFS(IF(ISEVEN('07.DRW'!$K$4),INDEX(Table1[],,10),INDEX(Table1[],,11)), Table1[[Customer name]:[Customer name]], '02.MIS Report Table'!$A17, Table1[[Payment Method]:[Payment Method]], "Online", Table1[[Product]:[Product]], '02.MIS Report Table'!E$6) -> 2046.24 | F17: =SUMIFS(IF(ISEVEN('07.DRW'!$K$4),INDEX(Table1[],,10),INDEX(Table1[],,11)), Table1[[Customer name]:[Customer name]], '02.MIS Report Table'!$A17, Table1[[Payment Method]:[Payment Method]], "Online", Table1[[Product]:[Product]], '02.MIS Report Table'!F$6) -> 60373.1 | G17: =SUMIFS(IF(ISEVEN('07.DRW'!$K$4),INDEX(Table1[],,10),INDEX(Table1[],,11)), Table1[[Customer name]:[Customer name]], '02.MIS Report Table'!$A17, Table1[[Payment Method]:[Payment Method]], "Online", Table1[[Product]:[Product]], '02.MIS Report Table'!G$6) -> 0 | H17: =SUMIFS(IF(ISEVEN('07.DRW'!$K$4),INDEX(Table1[],,10),INDEX(Table1[],,11)), Table1[[Customer name]:[Customer name]], '02.MIS Report Table'!$A17, Table1[[Payment Method]:[Payment Method]], "Online", Table1[[Product]:[Product]], '02.MIS Report Table'!H$6) -> 77419.44 | I17: =SUMIFS(IF(ISEVEN('07.DRW'!$K$4),INDEX(Table1[],,10),INDEX(Table1[],,11)), Table1[[Customer name]:[Customer name]], '02.MIS Report Table'!$A17, Table1[[Payment Method]:[Payment Method]], "Online", Table1[[Product]:[Product]], '02.MIS Report Table'!I$6) -> 3989.52 | J17: =SUMIFS(IF(ISEVEN('07.DRW'!$K$4),INDEX(Table1[],,10),INDEX(Table1[],,11)), Table1[[Customer name]:[Customer name]], '02.MIS Report Table'!$A17, Table1[[Payment Method]:[Payment Method]], "Cash", Table1[[Product]:[Product]], '02.MIS Report Table'!B$6) -> 0 | K17: =SUMIFS(IF(ISEVEN('07.DRW'!$K$4),INDEX(Table1[],,10),INDEX(Table1[],,11)), Table1[[Customer name]:[Customer name]], '02.MIS Report Table'!$A17, Table1[[Payment Method]:[Payment Method]], "Cash", Table1[[Product]:[Product]], '02.MIS Report Table'!C$6) -> 0 | L17: =SUMIFS(IF(ISEVEN('07.DRW'!$K$4),INDEX(Table1[],,10),INDEX(Table1[],,11)), Table1[[Customer name]:[Customer name]], '02.MIS Report Table'!$A17, Table1[[Payment Method]:[Payment Method]], "Cash", Table1[[Product]:[Product]], '02.MIS Report Table'!D$6) -> 2075.64 | M17: =SUMIFS(IF(ISEVEN('07.DRW'!$K$4),INDEX(Table1[],,10),INDEX(Table1[],,11)), Table1[[Customer name]:[Customer name]], '02.MIS Report Table'!$A17, Table1[[Payment Method]:[Payment Method]], "Cash", Table1[[Product]:[Product]], '02.MIS Report Table'!E$6) -> 0 | N17: =SUMIFS(IF(ISEVEN('07.DRW'!$K$4),INDEX(Table1[],,10),INDEX(Table1[],,11)), Table1[[Customer name]:[Customer name]], '02.MIS Report Table'!$A17, Table1[[Payment Method]:[Payment Method]], "Cash", Table1[[Product]:[Product]], '02.MIS Report Table'!F$6) -> 0 | O17: =SUMIFS(IF(ISEVEN('07.DRW'!$K$4),INDEX(Table1[],,10),INDEX(Table1[],,11)), Table1[[Customer name]:[Customer name]], '02.MIS Report Table'!$A17, Table1[[Payment Method]:[Payment Method]], "Cash", Table1[[Product]:[Product]], '02.MIS Report Table'!G$6) -> 23515.84 | P17: =SUMIFS(IF(ISEVEN('07.DRW'!$K$4),INDEX(Table1[],,10),INDEX(Table1[],,11)), Table1[[Customer name]:[Customer name]], '02.MIS Report Table'!$A17, Table1[[Payment Method]:[Payment Method]], "Cash", Table1[[Product]:[Product]], '02.MIS Report Table'!H$6) -> 24192.75 | Q17: =SUMIFS(IF(ISEVEN('07.DRW'!$K$4),INDEX(Table1[],,10),INDEX(Table1[],,11)), Table1[[Customer name]:[Customer name]], '02.MIS Report Table'!$A17, Table1[[Payment Method]:[Payment Method]], "Cash", Table1[[Product]:[Product]], '02.MIS Report Table'!I$6) -> 19723.2 | R17: =SUM(B17:Q17) -> 364922.49
A18: Total | B18: =SUM(B7:B17) -> 408777.2 | C18: =SUM(C7:C17) -> 574591.11 | D18: =SUM(D7:D17) -> 525382.25 | E18: =SUM(E7:E17) -> 304217.32 | F18: =SUM(F7:F17) -> 138896.4 | G18: =SUM(G7:G17) -> 348399.24 | H18: =SUM(H7:H17) -> 327336.28 | I18: =SUM(I7:I17) -> 327682.08 | ... R18: =SUM(R7:R17) -> 5603323.6

Sheet 04.Report
A1: Payment type by Product Revenue Report
A3: Payment Method | B3: Product | C3: Total Buying | D3: Total Sales | E3: Total Profit
A4: Cash | B4: Headphones | C4: 2222663.3 | D4: 2605472 | E4: 353979.65
B5: Keyboard | C5: 1600327.7 | D5: 1716530 | E5: 322670.25
B6: Laptop | C6: 1530606.7 | D6: 1728541 | E6: 197934.3
B7: Monitor | C7: 1365813.8 | D7: 1587981 | E7: 260293.17
B8: Mouse | C8: 2719610.8 | D8: 2520937 | E8: 450743.17
B9: Printer | C9: 2346270 | D9: 2913564 | E9: 393164.2
B10: Tablet | C10: 2371527.5 | D10: 2679963 | E10: 337433.49
B11: Webcam | C11: 2084165.5 | D11: 2727303 | E11: 331823.45
A12: Cash Total | C12: 16240986 | D12: 18480291 | E12: 2648041.7
A13: Online | B13: Headphones | C13: 2547423.8 | D13: 2918683 | E13: 408777.2
B14: Keyboard | C14: 3218809.5 | D14: 3740479 | E14: 574591.11
B15: Laptop | C15: 2897412.7 | D15: 2869945 | E15: 525382.25
B16: Monitor | C16: 1684730.7 | D16: 1811860 | E16: 304217.32
B17: Mouse | C17: 2484529 | D17: 3402974 | E17: 138896.4
B18: Printer | C18: 2038034.8 | D18: 2408409 | E18: 348399.24
B19: Tablet | C19: 2113037.2 | D19: 2509567 | E19: 327336.28
B20: Webcam | C20: 1945089.9 | D20: 1692256 | E20: 327682.08
A21: Online Total | C21: 18929068 | D21: 21354173 | E21: 2955281.9
A23: Grand Total | C23: 35170053 | D23: 39834464 | E23: 5603323.6

Sheet 03.Report
A1: Payment type by Customer Revenue Report
A3: Payment Method | B3: Customer name | C3: Total Buying | D3: Total Sales | E3: Total Profit
A4: Cash | B4: Anita | C4: 1383978.7 | D4: 1690529 | E4: 266474.3
B5: Karan | C5: 1260089.3 | D5: 1264629 | E5: 182364.7
B6: Neha | C6: 1613003.1 | D6: 1950007 | E6: 261778.05
B7: Pooja | C7: 1799424.6 | D7: 1934705 | E7: 241104.41
B8: Priya | C8: 443035.57 | D8: 492435 | E8: 69507.43
B9: Priya Gupta | C9: 1285022.8 | D9: 1511726 | E9: 226703.19
B10: Rahul | C10: 2478485.1 | D10: 2621012 | E10: 356881.91
B11: Shivam | C11: 1541733.8 | D11: 1797955 | E11: 303149.17
B12: Sneha | C12: 1060171.9 | D12: 1300094 | E12: 184314.14
B13: Sneha Gupta | C13: 888284.88 | D13: 1039999 | E13: 151714.12
B14: Vikram | C14: 2487755.7 | D14: 2877200 | E14: 404050.26
A15: Cash Total | C15: 16240986 | D15: 18480291 | E15: 2648041.7
A16: Online | B16: Anita | C16: 926446.59 | D16: 1200316 | E16: -9992.43
B17: Karan | C17: 2558076.3 | D17: 2625208 | E17: 440797.58
B18: Neha | C18: 1203039 | D18: 1333669 | E18: 168148.05
B19: Pooja | C19: 1454294.9 | D19: 1504999 | E19: 243510.05
B20: Priya | C20: 2110650.5 | D20: 2432255 | E20: 295415.06
B21: Priya Gupta | C21: 2203148.4 | D21: 2591030 | E21: 376445.73
B22: Rahul | C22: 1949211.6 | D22: 2533697 | E22: 334613.43
B23: Shivam | C23: 2603846.8 | D23: 2256907 | E23: 434471.2
B24: Sneha | C24: 2334173 | D24: 3031443 | E24: 580576.73
B25: Sneha Gupta | C25: 938300.1 | D25: 1050571 | E25: -32926
B26: Vikram | C26: 647880.52 | D26: 794078 | E26: 124222.48
A27: Online Total | C27: 18929068 | D27: 21354173 | E27: 2955281.9
A29: Grand Total | C29: 35170053 | D29: 39834464 | E29: 5603323.6

Sheet 05.Report
A1: State by City Revenue Reports
A3: States | B3: City | C3: Total Buying | D3: Total Sales | E3: Total Profit
A4: Delhi | B4: Connaught Place | C4: 314274.72 | D4: 361437 | E4: 47162.28
B5: Dwarka | C5: 820593.17 | D5: 837721 | E5: 156655.83
B6: Karol Bagh | C6: 1671318.1 | D6: 1943411 | E6: 255625.86
B7: New Delhi | C7: 918451.65 | D7: 927123 | E7: 143463.35
B8: Rohini | C8: 1159425.5 | D8: 1153693 | E8: 172092.45
B9: Saket | C9: 834087.75 | D9: 717140 | E9: 139827.25
A10: Delhi Total | C10: 5718151 | D10: 5940525 | E10: 914827.02
A11: Gujarat | B11: Ahmedabad | C11: 393656.4 | D11: 479662 | E11: 70115.6
B12: Bhavnagar | C12: 452736.88 | D12: 463985 | E12: 129721
B13: Jamnagar | C13: 1518481.9 | D13: 1767240 | E13: 240661.69
B14: Rajkot | C14: 1533762.7 | D14: 1811163 | E14: 292006.29
B15: Surat | C15: 769346.56 | D15: 865578 | E15: -48965.46
B16: Vadodara | C16: 789030.44 | D16: 936112 | E16: 147081.56
A17: Gujarat Total | C17: 5457014.9 | D17: 6323740 | E17: 830620.68
A18: Karnataka | B18: Belagavi | C18: 1198896.4 | D18: 1046495 | E18: 204766.56
B19: Bengaluru | C19: 1102566.9 | D19: 1584478 | E19: 199874.05
B20: Davanagere | C20: 1438892 | D20: 1954371 | E20: 267978.99
B21: Hubballi | C21: 1619626.3 | D21: 1985496 | E21: 314566.72
B22: Mangaluru | C22: 721258.7 | D22: 663951 | E22: 133255.3
B23: Mysuru | C23: 813724.01 | D23: 764426 | E23: 142563.99
A24: Karnataka Total | C24: 6894964.4 | D24: 7999217 | E24: 1263005.6
A25: Maharashtra | B25: Aurangabad | C25: 1568648.2 | D25: 1813907 | E25: 245258.8
B26: Mumbai | C26: 790580.36 | D26: 1364822 | E26: 21610.04
B27: Nagpur | C27: 307608.38 | D27: 358778 | E27: 51169.62
B28: Nashik | C28: 839630.96 | D28: 992298 | E28: 136335.04
B29: Pune | C29: 806209.44 | D29: 869318 | E29: 95031.56
B30: Thane | C30: 719478.71 | D30: 797845 | E30: 124934.81
A31: Maharashtra Total | C31: 5032156 | D31: 6196968 | E31: 674339.87
A32: Tamil Nadu | B32: Chennai | C32: 834980.46 | D32: 828148 | E32: 124757.54
B33: Coimbatore | C33: 1843524.6 | D33: 1667392 | E33: 529756.28
B34: Madurai | C34: 1004131.4 | D34: 1650472 | E34: 172329.59
B35: Salem | C35: 1655111.8 | D35: 1861634 | E35: 284711.17
B36: Tirunelveli | C36: 875781.72 | D36: 1047751 | E36: 156043.28
B37: Trichy | C37: 372551.84 | D37: 393527 | E37: 48932.16
A38: Tamil Nadu Total | C38: 6586081.9 | D38: 7448924 | E38: 1316530
A39: Uttar Pradesh | B39: Agra | C39: 597849.97 | D39: 618198 | E39: 76981.03
B40: Ghaziabad | C40: 1302878.9 | D40: 1473522 | E40: 170643.07
B41: Kanpur | C41: 1266126.1 | D41: 1433910 | E41: 205301.87
B42: Lucknow | C42: 965138.83 | D42: 967084 | E42: 91652.27
B43: Noida | C43: 501910.94 | D43: 403372 | E43: 84597.06
B44: Varanasi | C44: 847780.1 | D44: 1029004 | E44: -25174.94
A45: Uttar Pradesh Total | C45: 5481684.9 | D45: 5925090 | E45: 604000.36
A46: Grand Total | C46: 35170053 | D46: 39834464 | E46: 5603323.6

Sheet 06.Dashboard

Sheet 07.DRW
B1: DRW - Dashboard Row Work
N2: KPIs
A3: Row Labels | B3: Sum of Profit | C3: Sum of Total Sales | K3: Sheet 2 button
A4: Anita | B4: 256481.87 | C4: 2890845 | K4: 14963 | N4: Top Product | O4: Top Customer | P4: Total Sales | Q4: Total Profit
A5: Karan | B5: 623162.28 | C5: 3889837 | N5: =E10 -> Keyboard | O5: =E14 -> Sneha | P5: =GETPIVOTDATA("Total Sales",$K$9) -> 39834464 | Q5: =GETPIVOTDATA("Profit",$H$9) -> 5603323.6
A6: Neha | B6: 429926.1 | C6: 3283676
A7: Pooja | B7: 484614.46 | C7: 3439704
A8: Priya | B8: 364922.49 | C8: 2924690
A9: Priya Gupta | B9: 603148.92 | C9: 4102756 | E9: Row Labels | F9: Sum of Profit | H9: Row Labels | I9: Sum of Profit | K9: Row Labels | L9: Sum of Total Sales
A10: Rahul | B10: 691495.34 | C10: 5154709 | E10: Keyboard | F10: 897261.36 | H10: Delhi | I10: 914827.02 | K10: Delhi | L10: 5940525
A11: Shivam | B11: 737620.37 | C11: 4054862 | E11: Grand Total | F11: 897261.36 | H11: Gujarat | I11: 830620.68 | K11: Gujarat | L11: 6323740
A12: Sneha | B12: 764890.87 | C12: 4331537 | H12: Karnataka | I12: 1263005.6 | K12: Karnataka | L12: 7999217
A13: Sneha Gupta | B13: 118788.12 | C13: 2090570 | E13: Row Labels | F13: Sum of Profit | H13: Maharashtra | I13: 674339.87 | K13: Maharashtra | L13: 6196968
A14: Vikram | B14: 528272.74 | C14: 3671278 | E14: Sneha | F14: 764890.87 | H14: Tamil Nadu | I14: 1316530 | K14: Tamil Nadu | L14: 7448924
A15: Grand Total | B15: 5603323.6 | C15: 39834464 | E15: Grand Total | F15: 764890.87 | H15: Uttar Pradesh | I15: 604000.36 | K15: Uttar Pradesh | L15: 5925090
H16: Grand Total | I16: 5603323.6 | K16: Grand Total | L16: 39834464
B19: Row Labels | C19: Sum of Profit
B20: Headphones | C20: 762756.85
B21: Keyboard | C21: 897261.36
B22: Laptop | C22: 723316.55
B23: Monitor | C23: 564510.49
B24: Mouse | C24: 589639.57
B25: Printer | C25: 741563.44 | E25: Row Labels | F25: Sum of Total Sales | H25: Row Labels | I25: Sum of Total Sales
B26: Tablet | C26: 664769.77 | E26: Cash | F26: 18480291 | H26: Cash | I26: 18480291
B27: Webcam | C27: 659505.53 | E27: Online | F27: 21354173 | H27: Online | I27: 21354173
B28: Grand Total | C28: 5603323.6 | E28: Grand Total | F28: 39834464 | H28: Grand Total | I28: 39834464
